Workbook

Sheet ASVS Results
A1: Security Category | B1: Valid criteria | C1: Total criteria | D1: Validity Percentage | E1: ASVS Level Acquired
A2: Architecture, Design and Threat Modeling | B2: =0+COUNTIF('Architecture, Design and Threat'!G2:G45,"Valid") -> 33 | C2: =COUNTIF('Architecture, Design and Threat'!G2:G45,"<>Not Applicable") -> 39 | D2: =(B2/C2)*100 -> 84.615385 | F2: Diana
A3: Authentication | B3: =COUNTIF(Authentication!G2:G58,"Valid") -> 22 | C3: =COUNTIF(Authentication!G2:G58,"<>Not Applicable") -> 50 | D3: =(B3/C3)*100 -> 44 | F3: Diogo/Pedros
A4: Session Management | B4: =COUNTIF('Session Management'!G2:G21,"Valid") -> 13 | C4: =COUNTIF('Session Management'!G2:G21,"<>Not Applicable") -> 17 | D4: =(B4/C4)*100 -> 76.470588 | F4: Pedro C
A5: Access Control | B5: =COUNTIF('Access Control'!G2:G11,"Valid") -> 8 | C5: =COUNTIF('Access Control'!G2:G11,"<>Not Applicable") -> 9 | D5: =(B5/C5)*100 -> 88.888889 | F5: Pedro C
A6: Validation, Sanitization and Encoding | B6: =COUNTIF('Validation, Sanitization and En'!G2:G31,"Valid") -> 18 | C6: =COUNTIF('Validation, Sanitization and En'!G2:G31,"<>Not Applicable") -> 30 | D6: =(B6/C6)*100 -> 60 | F6: Pedro C
A7: Stored Cryptography | B7: =COUNTIF('Stored Cryptography'!G2:G17,"Valid") -> 8 | C7: =COUNTIF('Stored Cryptography'!G2:G17,"<>Not Applicable") -> 16 | D7: =(B7/C7)*100 -> 50 | F7: Diana
A8: Error Handling and Logging | B8: =COUNTIF('Error Handling and Logging'!G2:G14,"Valid") -> 7 | C8: =COUNTIF('Error Handling and Logging'!G2:G14,"<>Not Applicable") -> 12 | D8: =(B8/C8)*100 -> 58.333333 | F8: Diogo
A9: Data Protection | B9: =COUNTIF('Data Protection'!G2:G18,"Valid") -> 8 | C9: =COUNTIF('Data Protection'!G2:G18,"<>Not Applicable") -> 17 | D9: =(B9/C9)*100 -> 47.058824 | F9: Diogo
A10: Communication | B10: =COUNTIF(Communication!G2:G9,"Valid") -> 6 | C10: =COUNTIF(Communication!G2:G9,"<>Not Applicable") -> 8 | D10: =(B10/C10)*100 -> 75 | F10: Diogo
A11: Malicious Code | B11: =COUNTIF('Malicious Code'!G2:G11,"Valid") -> 7 | C11: =COUNTIF('Malicious Code'!G2:G11,"<>Not Applicable") -> 7 | D11: =(B11/C11)*100 -> 100 | F11: Pedro V
A12: Business Logic | B12: =COUNTIF('Business Logic'!G2:G9,"Valid") -> 5 | C12: =COUNTIF('Business Logic'!G2:G9,"<>Not Applicable") -> 8 | D12: =(B12/C12)*100 -> 62.5 | F12: Pedro V
A13: Files and Resources | B13: =COUNTIF('Files and Resources'!G2:G16,"Valid") -> 9 | C13: =COUNTIF('Files and Resources'!G2:G16,"<>Not Applicable") -> 13 | D13: =(B13/C13)*100 -> 69.230769 | F13: Pedro V
A14: API and Web Service | B14: =COUNTIF('API and Web Service'!G2:G16,"Valid") -> 8 | C14: =COUNTIF('API and Web Service'!G2:G16,"<>Not Applicable") -> 9 | D14: =(B14/C14)*100 -> 88.888889 | F14: Pedro V
A15: Configuration | B15: =COUNTIF(Configuration!G2:G26,"Valid") -> 18 | C15: =COUNTIF(Configuration!G2:G26,"<>Not Applicable") -> 23 | D15: =(B15/C15)*100 -> 78.26087 | F15: Diogo
A16: Total | B16: =SUM(B2:B15) -> 170 | C16: =SUM(C2:C15) -> 258 | D16: =(B16/C16)*100 -> 65.891473

Sheet Architecture, Design and Threat
A1: Area | B1: # | C1: ASVS Level | D1: CWE | E1: NIST | F1: Verification Requirement | G1: Valid | H1: Source Code Reference | I1: Comment | J1: Tool Used
A2: Secure Software Development Lifecycle | B2: 1.1.1 | C2: 2 | F2: Verify the use of a secure software development lifecycle that addresses security in all stages of development. ([C1](https://owasp.org/www-project-proactive-controls/#div-numbering)) | G2: Valid | H2: Relatório Fase 1 | I2: Ao longo de todos os sprints do projeto, a equipa tem realizado uma identificação contínua e sistemática dos aspetos de segurança relevantes para cada fase do desenvolvimento. Esta prática assegura que a segurança é considerada desde a conceção até à implementação, alinhando-se com as melhores práticas de um ciclo de vida de desenvolvimento seguro (SDLC). A modelação de ameaças, análise de riscos e definição de contramedidas são atividades integradas nas reuniões de planeamento e revisões, garantindo que potenciais vulnerabilidades são antecipadas e tratadas atempadamente.
B3: 1.1.2 | C3: 2 | D3: 1053 | F3: Verify the use of threat modeling for every design change or sprint planning to identify threats, plan for countermeasures, facilitate appropriate risk responses, and guide security testing. | G3: Valid | H3: Relatório Fase 1 | I3: A modelação de ameaças foi realizada na Fase 1 do projeto e continuará a ser efetuada nas fases seguintes e em cada alteração de design ou sprint, garantindo a identificação e mitigação contínua dos riscos de segurança.
B4: 1.1.3 | C4: 2 | D4: 1110 | F4: Verify that all user stories and features contain functional security constraints, such as "As a user, I should be able to view and edit my profile. I should not be able to view or edit anyone else's profile" | G4: Valid | H4: Relatório Fase 1 | I4: Para cada elemento do Diagrama de Fluxo de Dados (DFD) foram elaborados casos de abuso, identificando vetores de ataque e agentes de ameaça associados. Além disso, todas as user stories e funcionalidades incorporam restrições funcionais de segurança, assegurando que os requisitos de proteção são considerados desde a definição das funcionalidades. | J4: OWASP Threat Dragon - DFDs diagrams
B5: 1.1.4 | C5: 2 | D5: 1059 | F5: Verify documentation and justification of all the application's trust boundaries, components, and significant data flows. | G5: Valid | H5: Relatório Fase 1 | I5: Foram elaborados Diagramas de Fluxo de Dados (DFD) que indicam claramente as fronteiras de confiança, as ameaças associadas e o fluxo dos dados significativos no sistema. Esta documentação permite uma melhor compreensão e análise dos pontos críticos de segurança. | J5: OWASP Threat Dragon - DFDs diagrams
B6: 1.1.5 | C6: 2 | D6: 1059 | F6: Verify definition and security analysis of the application's high-level architecture and all connected remote services. ([C1](https://owasp.org/www-project-proactive-controls/#div-numbering)) | G6: Valid | H6: Fase 2 - Sprint 1 --> DTOS implementados | I6: Elaborámos diagramas de componentes e Diagramas de Fluxo de Dados (DFDs) e verificámos que a arquitetura do projeto não incluía Data Transfer Objects (DTOs). Por essa razão, a implementação dos DTOs foi realizada neste Sprint 1 da Fase 2, garantindo uma definição mais clara e segura da arquitetura de alto nível e dos serviços remotos associados.
B7: 1.1.6 | C7: 2 | D7: 637 | F7: Verify implementation of centralized, simple (economy of design), vetted, secure, and reusable security controls to avoid duplicate, missing, ineffective, or insecure controls. ([C10](https://owasp.org/www-project-proactive-controls/#div-numbering)) | G7: Valid | H7: Relatório Fase 1 | I7: Utilizamos sempre a mesma biblioteca para funções específicas, como autenticação e validação, garantindo a reutilização de código e a implementação de controlos de segurança centralizados, simples e seguros em todo o projeto.
B8: 1.1.7 | C8: 2 | D8: 637 | F8: Verify availability of a secure coding checklist, security requirements, guideline, or policy to all developers and testers. | G8: Valid | H8: Fase 2 - Sprint 1 | I8: Estamos a usar o ASVS como referência de segurança, integrado na pipeline de desenvolvimento e com revisões de código regulares, para garantir que todos seguem boas práticas de codificação segura. | J8: OWASP ASVS, GIT HUB
A9: Authentication Architecture | B9: 1.2.1 | C9: 2 | D9: 250 | F9: Verify the use of unique or special low-privilege operating system accounts for all application components, services, and servers. ([C3](https://owasp.org/www-project-proactive-controls/#div-numbering)) | G9: Valid | H9: Ainda não está completo, falta fazer o deploy na pipeline | I9: No estado atual, a pipeline CI/CD garante que as fases de build, teste e análise são executadas com permissões mínimas, conforme os runners da GitHub. No entanto, o passo de deploy ainda não está configurado para um ambiente real. Na fase seguinte, será necessário garantir que, em produção, os serviços correm com utilizadores com permissões limitadas
B10: 1.2.2 | C10: 2 | D10: 306 | F10: Verify that communications between application components, including APIs, middleware and data layers, are authenticated. Components should have the least necessary privileges needed. ([C3](https://owasp.org/www-project-proactive-controls/#div-numbering)) | G10: Valid | H10: appsettings.json: "ConnectionStrings": { "DefaultConnection": "Server=myserver;Database=mydb;User Id=myuser;Password=mypassword;" } | I10: A comunicação entre a aplicação e a base de dados é autenticada via connection string com credenciais específicas.
B11: 1.2.3 | C11: 2 | D11: 306 | F11: Verify that the application uses a single vetted authentication mechanism that is known to be secure, can be extended to include strong authentication, and has sufficient logging and monitoring to detect account abuse or breaches. | G11: Valid | H11: Colocar posteriormente logging para monitorizar. Program.cs: Autenticação por cookie: builder.Services.ConfigureApplicationCookie(options => { ... options.Cookie.SecurePolicy = CookieSecurePolicy.Always; options.Cookie.SameSite = SameSiteMode.Strict; }); Suporte a roles e política de autorização: builder.Services.AddAuthorization(options => { options.AddPolicy("Manager", policy => policy.RequireRole("Manager")); }); Suporte a extensibilidade via Identity: builder.Services.AddIdentity<AppUser, IdentityRole>() .AddEntityFrameworkStores<AppDbContext>() .AddDefaultTokenProviders(); | I11: Atualmente, a aplicação utiliza autenticação baseada em cookies com o ASP.NET Core Identity, um mecanismo seguro e extensível. Embora o sistema ainda não tenha um mecanismo de monitorização ativo, a arquitetura permite integrar facilmente logging e auditoria de acessos, através de ILogger, Application Insights, Serilog, ou outros sistemas compatíveis com .NET. A monitorização será considerada numa fase posterior do projeto. | J11: Identity (ASP.NET Core)
B12: 1.2.4 | C12: 2 | D12: 306 | F12: Verify that all authentication pathways and identity management APIs implement consistent authentication security control strength, such that there are no weaker alternatives per the risk of the application. | G12: Valid | H12: Program.cs: builder.Services.AddIdentity<AppUser, IdentityRole>() .AddEntityFrameworkStores<AppDbContext>() .AddDefaultTokenProviders(); builder.Services.ConfigureApplicationCookie(options => { options.LoginPath = "/api/account/login"; options.LogoutPath = "/api/account/logout"; options.SlidingExpiration = true; options.Cookie.SecurePolicy = CookieSecurePolicy.Always; options.Cookie.SameSite = SameSiteMode.Strict; }); | I12: Mecanismo de autenticação unificado e seguro com base em cookies. | J12: Identity (ASP.NET Core)
A13: Session Management Architecture | F13: This is a placeholder for future architectural requirements. | G13: Not Applicable
A14: Access Control Architecture | B14: 1.4.1 | C14: 2 | D14: 602 | F14: Verify that trusted enforcement points such as at access control gateways, servers, and serverless functions enforce access controls. Never enforce access controls on the client. | G14: Valid | H14: Program.cs and SubscriptionPeriodController.cs: // Em Program.cs: builder.Services.AddIdentity<AppUser, IdentityRole>() .AddEntityFrameworkStores<AppDbContext>() .AddDefaultTokenProviders(); // Configuração das policies: builder.Services.AddAuthorization(options => { options.AddPolicy("Manager", policy => policy.RequireRole("Manager")); options.AddPolicy("Producer", policy => policy.RequireRole("Producer")); options.AddPolicy("CoProducer", policy => policy.RequireRole("CoProducer")); }); // Middleware na pipeline: app.UseAuthentication(); app.UseAuthorization(); // No controller: [Authorize(Roles = nameof(UserType.Manager))] [HttpPost()] public async Task<IActionResult> CreateSubscriptionPeriodAndDeliveryDate(...) { // método protegido por policy de roles } | I14: Controlos de acesso aplicados exclusivamente no backend, usando middleware de autenticação/autorização e atributos [Authorize]. O frontend não valida permissões. | J14: ASP.NET Core Identity, Middleware ASP.NET Core
B15: 1.4.2 | C15: 2 | D15: 284 | F15: [DELETED, NOT ACTIONABLE] | G15: Not Applicable
B16: 1.4.3 | C16: 2 | D16: 272 | F16: [DELETED, DUPLICATE OF 4.1.3] | G16: Not Applicable
B17: 1.4.4 | C17: 2 | D17: 284 | F17: Verify the application uses a single and well-vetted access control mechanism for accessing protected data and resources. All requests must pass through this single mechanism to avoid copy and paste or insecure alternative paths. ([C7](https://owasp.org/www-project-proactive-controls/#div-numbering)) | G17: Valid | H17: Program.cs and SubscriptionPeriodController.cs. | I17: A aplicação assegura acesso uniforme através de Identity e políticas, evitando caminhos alternativos inseguros. | J17: ASP.NET Core Authorization
B18: 1.4.5 | C18: 2 | D18: 275 | F18: Verify that attribute or feature-based access control is used whereby the code checks the user's authorization for a feature/data item rather than just their role. Permissions should still be allocated using roles. ([C7](https://owasp.org/www-project-proactive-controls/#div-numbering)) | G18: Valid | H18: Program.cs: builder.Services.AddIdentity<AppUser, IdentityRole>() .AddEntityFrameworkStores<AppDbContext>() .AddDefaultTokenProviders(); builder.Services.AddAuthorization(options => { options.AddPolicy("CanImportProducts", policy => policy.RequireClaim("CanImport", "true")); }); app.UseAuthentication(); app.UseAuthorization(); ProductController.cs: [Authorize(Roles = nameof(UserType.Producer))] public class ProductController : ControllerBase { [HttpPost("import-from-file")] [Authorize(Policy = "CanImportProducts")] // controlo baseado em claim/atributo public IActionResult ImportProductsFromFile(IFormFile file) { // implementação omitida return Ok(); } } | I18: Utiliza-se o ASP.NET Core Identity para roles, complementado com validações específicas baseadas em claims (atributos) do utilizador para decisões de negócio. | J18: ASP.NET Core Identity
A19: Input and Output Architecture | B19: 1.5.1 | C19: 2 | D19: 1029 | F19: Verify that input and output requirements clearly define how to handle and process data based on type, content, and applicable laws, regulations, and other policy compliance. | G19: Valid | H19: ProductOfferController.cs: if(productOffer == null) return BadRequest(); catch(ArgumentException) { return BadRequest(); } | I19: Validação de dados e tratamento de erros implementados no controller para garantir dados corretos e conformidade. | J19: ASP.NET Core MVC
B20: 1.5.2 | C20: 2 | D20: 502 | F20: Verify that serialization is not used when communicating with untrusted clients. If this is not possible, ensure that adequate integrity controls (and possibly encryption if sensitive data is sent) are enforced to prevent deserialization attacks including object injection. | G20: Valid | H20: ProductOfferController.cs: [HttpPost] public IActionResult CreateProductOffer([FromBody] ProductOffer productOffer) { ... } Program.cs: builder.Services.AddControllers().AddJsonOptions(...) | I20: Desserialização JSON feita automaticamente via [FromBody] em modelos fortemente tipados, o que limita a superfície para ataques. Configuração padrão do System.Text.Json previne tipos arbitrários. | J20: System.Text.Json/ASP.NET Core
B21: 1.5.3 | C21: 2 | D21: 602 | F21: Verify that input validation is enforced on a trusted service layer. ([C5](https://owasp.org/www-project-proactive-controls/#div-numbering)) | G21: Valid | H21: if (ModelState.IsValid) em AccountController.cs; if (productOffer == null) em ProductOfferController.cs; if (subscription.ExpectedQuantity <= 0) em SubscriptionController.cs; [Authorize(Roles = nameof(UserType.Producer))] em vários controllers; if (!Enum.IsDefined(typeof(PaymentType), subscription.PaymentType)) em SubscriptionController.cs | I21: Validações e restrições feitas no backend, garantindo que todos os dados recebidos são verificados antes do processamento
B22: 1.5.4 | C22: 2 | D22: 116 | F22: Verify that output encoding occurs close to or by the interpreter for which it is intended. ([C4](https://www.owasp.org/index.php/OWASP_Proactive_Controls#tab=Formal_Numbering)) | G22: Valid | H22: return Ok(obj) em vários controllers; uso de JSON serialization padrão (System.Text.Json/Newtonsoft.Json) | I22: O backend apenas serializa dados para JSON, sem gerar HTML; a codificação de saída para XSS deve ser feita no frontend
A23: Cryptographic Architecture | B23: 1.6.1 | C23: 2 | D23: 320 | F23: Verify that there is an explicit policy for management of cryptographic keys and that a cryptographic key lifecycle follows a key management standard such as NIST SP 800-57. | G23: Non-valid | H23: Implementar o ASP.NET Core Data Protection com persistência das chaves no Azure Key Vault, garantindo que todas as chaves criptográficas usadas pela aplicação são geridas, protegidas e rotacionadas automaticamente conforme as melhores práticas do NIST. | I23: A clear key management policy reduces risks of exposure and misuse (risks 5.1 I, 3.3 I). It is recommended to follow NIST SP 800-57. | J23: Azure Key Vault, AWS KMS
B24: 1.6.2 | C24: 2 | D24: 320 | F24: Verify that consumers of cryptographic services protect key material and other secrets by using key vaults or API based alternatives. | G24: Non-valid | H24: Recomendada a externalização de todos os segredos sensíveis (como connection strings, passwords e chaves de API) para um serviço seguro, como o Azure Key Vault. A aplicação deve ser configurada para aceder a estes segredos de forma automática e segura, utilizando, por exemplo, o método builder.Configuration.AddAzureKeyVault(...) no ficheiro Program.cs | I24: Storing secrets in vaults prevents accidental exposure and attacks (risks 5.1 I, 3.3 I). | J24: Azure Key Vault, AWS Secrets Manager.
B25: 1.6.3 | C25: 2 | D25: 320 | F25: Verify that all keys and passwords are replaceable and are part of a well-defined process to re-encrypt sensitive data. | G25: Non-valid | H25: Necessário externalizar as chaves e segredos sensíveis para um cofre seguro, como o Azure Key Vault, permitindo a sua rotação sem necessidade de alterar o código. Além disso, deve ser implementado um processo formal e documentado para a rotação periódica dessas chaves e para a re-encriptação dos dados sensíveis sempre que uma chave for substituída. | I25: Key and password rotation processes mitigate the impact of compromise (risks 5.1 I, 3.3 I). | J25: Azure Key Vault, rotation scripts
B26: 1.6.4 | C26: 2 | D26: 320 | F26: Verify that the architecture treats client-side secrets--such as symmetric keys, passwords, or API tokens--as insecure and never uses them to protect or access sensitive data. | G26: Valid | H26: Autenticação e autorização feitas apenas no backend (ex: [Authorize], ASP.NET Identity) | I26: Não há segredos armazenados ou utilizados no frontend; toda a proteção de dados é feita de forma segura no backend. | J26: ASP.NET Identity
A27: Error, Logging and Auditing Architecture | B27: 1.7.1 | C27: 2 | D27: 1009 | F27: Verify that a common logging format and approach is used across the system. ([C9](https://owasp.org/www-project-proactive-controls/#div-numbering)) | G27: Non-valid | H27: Necessário adicionar e utilizar o serviço ILogger<T> do ASP.NET Core em todos os controladores e serviços do projeto, garantindo que todas as operações relevantes sejam registadas de forma estruturada e consistente. | I27: Using a common log format facilitates analysis and incident detection (risks 4.3 R, 5.1 I). | J27: Default logging in ASP.NET Core
B28: 1.7.2 | C28: 2 | F28: Verify that logs are securely transmitted to a preferably remote system for analysis, detection, alerting, and escalation. ([C9](https://owasp.org/www-project-proactive-controls/#div-numbering)) | G28: Non-valid | H28: Adicionar e configurar o Serilog (ou outro logger estruturado) para enviar logs via HTTPS para um sistema remoto (ex: Seq, ELK, Splunk), garantindo que o endpoint remoto está protegido e que toda a transmissão dos logs é cifrada. | I28: Securely transmitting logs to a remote system reduces the risk of tampering or loss of evidence (risks 4.3 R, 5.1 I). | J28: Solutions like ELK Stack, Azure Monitor, or remote syslog.
A29: Data Protection and Privacy Architecture | B29: 1.8.1 | C29: 2 | F29: Verify that all sensitive data is identified and classified into protection levels. | G29: Valid | H29: AppUser | I29: Passwords protegidas pelo ASP.NET Identity; autenticação e sessão via cookies seguros; dados pessoais em entidades como AppUser | J29: ASP.NET Identity /Documentation
B30: 1.8.2 | C30: 2 | F30: Verify that all protection levels have an associated set of protection requirements, such as encryption requirements, integrity requirements, retention, privacy and other confidentiality requirements, and that these are applied in the architecture. | G30: Valid | H30: Hashing de passwords pelo ASP.NET Identity; configuração de HTTPS no Program.cs | I30: Requisitos de cifragem e comunicação segura aplicados | J30: Identity/Documentation
A31: Communications Architecture | B31: 1.9.1 | C31: 2 | D31: 319 | F31: Verify the application encrypts communications between components, particularly when these components are in different containers, systems, sites, or cloud providers. ([C3](https://owasp.org/www-project-proactive-controls/#div-numbering)) | G31: Valid | H31: app.UseHttpsRedirection() no Program.cs; string de ligação da base de dados pode ser configurada com Encrypt=True | I31: HTTPS garante cifragem nas comunicações externas; ligação à base de dados deve ser ajustada para usar encriptação
B32: 1.9.2 | C32: 2 | D32: 295 | F32: Verify that application components verify the authenticity of each side in a communication link to prevent person-in-the-middle attacks. For example, application components should validate TLS certificates and chains. | G32: Valid | H32: Uso padrão de HTTPS no Kestrel/ASP.NET Core | I32: Certificados TLS são validados automaticamente
A33: Malicious Software Architecture | B33: 1.10.1 | C33: 2 | D33: 284 | F33: Verify that a source code control system is in use, with procedures to ensure that check-ins are accompanied by issues or change tickets. The source code control system should have access control and identifiable users to allow traceability of any changes. | G33: Valid | I33: O projeto utiliza Git com repositório remoto no GitHub, cada membro tem conta identificável, os commits podem ser associados a issues e todas as alterações passam por pull requests, garantindo rastreabilidade, revisão e controlo de acesso. | J33: GitHub
A34: Business Logic Architecture | B34: 1.11.1 | C34: 2 | D34: 1059 | F34: Verify the definition and documentation of all application components in terms of the business or security functions they provide. | G34: Valid | I34: API documentada automaticamente via Swagger; controllers organizados por função de negócio/segurança; README com documentação relevante sobre arquitetura, fluxos e componentes do sistema | J34: Swagger + Controllers + README(Relatorio)
B35: 1.11.2 | C35: 2 | D35: 362 | F35: Verify that all high-value business logic flows, including authentication, session management and access control, do not share unsynchronized state. | G35: Valid | H35: builder.Services.AddScoped<...>() e builder.Services.AddSingleton<EmailSender>() no Program.cs | I35: Autenticação e sessões isoladas por utilizador; serviços críticos registados como Scoped, evitando partilha de estado; Singletons não armazenam dados sensíveis | J35: ASP.NET Identity, Cookies, Injeção de Dependências
B36: 1.11.3 | C36: 2 | D36: 367 | F36: Verify that all high-value business logic flows, including authentication, session management and access control are thread safe and resistant to time-of-check and time-of-use race conditions. | G36: Valid | H36: Uso padrão de controllers e serviços Scoped no Program.cs; autenticação e permissões via ASP.NET Identity | I36: Endpoints críticos são isolados por request; não há partilha de estado mutável; framework garante thread-safety; monitorizar futuros acessos a recursos partilhados | J36: ASP.NET Core Controllers, Identity
A37: Secure File Upload Architecture | B37: 1.12.1 | C37: 2 | D37: 552 | F37: [DELETED, DUPLICATE OF 12.4.1] | G37: Not Applicable
B38: 1.12.2 | C38: 2 | D38: 646 | F38: Verify that user-uploaded files - if required to be displayed or downloaded from the application - are served by either octet stream downloads, or from an unrelated domain, such as a cloud file storage bucket. Implement a suitable Content Security Policy (CSP) to reduce the risk from XSS vectors or other attacks from the uploaded file. | G38: Valid | H38: Exemplo: return File(fileContent, contentType, fileName); em ProductController | I38: Ficheiros não são renderizados, apenas servidos como download com tipo MIME apropriado; não há preview direto
A39: API Architecture | F39: This is a placeholder for future architectural requirements. | G39: Not Applicable
A40: Configuration Architecture | B40: 1.14.1 | C40: 2 | D40: 923 | F40: Verify the segregation of components of differing trust levels through well-defined security controls, firewall rules, API gateways, reverse proxies, cloud-based security groups, or similar mechanisms. | G40: Valid | I40: Backend com endpoints bem definidos, permitindo aplicação de regras de firewall, proxies reversos e segmentação de rede em produção
B41: 1.14.2 | C41: 2 | D41: 494 | F41: Verify that binary signatures, trusted connections, and verified endpoints are used to deploy binaries to remote devices. | G41: Valid | H41: Exemplo: uses: actions/checkout@v3, dotnet restore, dependency-check/Dependency-Check_Action@main na pipeline | I41: Deploy feito por pipeline autenticada, com análise de dependências e acesso seguro a segredos; | J41: GitHub Actions CI/CD
B42: 1.14.3 | C42: 2 | D42: 1104 | F42: Verify that the build pipeline warns of out-of-date or insecure components and takes appropriate actions. | G42: Valid | H42: Etapa Run SCA (OWASP Dependency Check) e dependency-check/Dependency-Check_Action@main na pipeline | I42: Dependabot alerta para dependências inseguras; pipeline executa análise automática de vulnerabilidades com OWASP Dependency-Check | J42: GitHub Dependabot + OWASP Dependency-Check
B43: 1.14.4 | C43: 2 | F43: Verify that the build pipeline contains a build step to automatically build and verify the secure deployment of the application, particularly if the application infrastructure is software defined, such as cloud environment build scripts. | G43: Non-valid | H43: Adicionar scripts de infraestrutura como código (ex: ARM, Bicep, Terraform) para definir e provisionar o ambiente Azure, e incluir na pipeline etapas de validação automática dessas configurações (ex: az bicep build, terraform validate, ou ferramentas de segurança como Checkov ou AzSK) para garantir que o deployment é seguro e conforme as melhores práticas. | I43: Automating and verifying deployment reduces manual errors and insecure configuration risks (risks 4.3 R, 5.1 I). | J43: CI/CD (GitHub Actions, Azure DevOps), validation scripts
B44: 1.14.5 | C44: 2 | D44: 265 | F44: Verify that application deployments adequately sandbox, containerize and/or isolate at the network level to delay and deter attackers from attacking other applications, especially when they are performing sensitive or dangerous actions such as deserialization. ([C5](https://owasp.org/www-project-proactive-controls/#div-numbering)) | G44: Valid | I44: Deploy em ambiente Azure isolado, com possibilidade de segmentação de rede; recomenda-se reforçar isolamento para operações sensíveis | J44: Azure App Service
B45: 1.14.6 | C45: 2 | D45: 477 | F45: Verify the application does not use unsupported, insecure, or deprecated client-side technologies such as NSAPI plugins, Flash, Shockwave, ActiveX, Silverlight, NACL, or client-side Java applets. | G45: Valid | I45: Não utiliza nem serve tecnologias cliente obsoletas ou inseguras; apenas expõe APIs RESTful modernas | J45: Code review, dependency analysis

Sheet Authentication
A1: Area | B1: # | C1: ASVS Level | D1: CWE | E1: NIST | F1: Verification Requirement | G1: Valid | H1: Source Code Reference | I1: Comment | J1: Tool Used
A2: Password Security -Pedro Vilarinho | B2: 2.1.1 | C2: 1 | D2: 521 | E2: 5.1.1.2 | F2: Verify that user set passwords are at least 12 characters in length (after multiple spaces are combined). ([C6](https://owasp.org/www-project-proactive-controls/#div-numbering)) | G2: Valid | H2: Program.cs:65 - options.Password.RequiredLength = 12; RegisterViewModel.cs:15 - [StringLength(128, MinimumLength = 12)] ChangePasswordViewModel.cs:12 - [StringLength(128, MinimumLength = 12)] | I2: Establishing a minimum password length of 12 characters is crucial to mitigate authentication-related threats, such as those identified with high severity in the DREAD analysis (#2, #7, #9, #10). Longer passwords significantly increase resistance against brute-force and dictionary attacks. This measure helps protect against "Identity spoofing to gain unauthorized access" and "Credential interception during transmission," which are critical threats in the AMAP system, especially considering access by different types of users (Managers, Producers, Co-Producers). | J2: Password validation libraries such as zxcvbn Password policy configuration in authentication frameworks Password strength validators on both frontend and backend
B3: 2.1.2 | C3: 1 | D3: 521 | E3: 5.1.1.2 | F3: Verify that passwords of at least 64 characters are permitted, and that passwords of more than 128 characters are denied. ([C6](https://owasp.org/www-project-proactive-controls/#div-numbering)) | G3: Valid | H3: Program.cs:162-169 - CustomPasswordValidator verifica password.Length > 128 RegisterViewModel.cs:15 - [StringLength(128, MinimumLength = 12)] ChangePasswordViewModel.cs:12 - [StringLength(128, MinimumLength = 12)] | I3: Allowing long passwords (up to 64 characters) while capping the maximum at 128 characters balances security and protection against DoS attacks. Longer passwords strengthen security against high-severity authentication-related threats identified in the DREAD analysis, such as "Identity spoofing to gain unauthorized access" (#7) and "Identity spoofing to bypass authentication" (#9). The upper limit of 128 characters protects against potential denial-of-service attacks based on extremely long passwords that could overwhelm the hashing process. | J3: ASP.NET Core Identity Framework - This is the authentication framework being used, which handles password validation through its configuration options and validators.
B4: 2.1.3 | C4: 1 | D4: 521 | E4: 5.1.1.2 | F4: Verify that password truncation is not performed. However, consecutive multiple spaces may be replaced by a single space. ([C6](https://owasp.org/www-project-proactive-controls/#div-numbering)) | G4: Valid | H4: Program.cs:173 - var normalizedPassword = Regex.Replace(password, @"\s+", " "); Program.cs:174-181 - Verifica normalizedPassword.Length < 12 após normalização | I4: Avoiding password truncation is essential to preserve the password’s entropy and strength as intended by the user. This practice prevents vulnerabilities related to various high-severity authentication threats identified in the DREAD analysis, such as "Identity spoofing to gain unauthorized access" (#7) and "Modification of credentials or tokens during transmission" (#8). Normalizing consecutive spaces into a single space is an acceptable compromise that avoids usability issues without significantly compromising security. Implementing this requirement is critical to protecting the accounts of all user profiles in the AMAP system (Managers, Producers, Co-Producers). | J4: Modern hashing algorithms that support long passwords (Argon2, bcrypt) Proper string processing for space normalization Automated tests to verify the correct behavior of the authentication system ASP.NET Core Identity for authentication management and password policies
B5: 2.1.4 | C5: 1 | D5: 521 | E5: 5.1.1.2 | F5: Verify that any printable Unicode character, including language neutral characters such as spaces and Emojis are permitted in passwords. | G5: Valid | H5: ASP.NET Core Identity already allows Unicode characters by default, so we don't need to add specific validation for this | I5: Allowing any printable Unicode character in passwords (including spaces and emojis) increases the available character space, making passwords stronger against brute-force attacks. This is particularly relevant considering the high-risk threats identified related to authentication and identity spoofing (threats #2, #7, #9, #10 in the DREAD list), such as "Identity spoofing to gain unauthorized access" and "Identity spoofing to bypass authentication. | J5: Password validation library that supports full Unicode Modern authentication framework (ASP.NET Identity)
B6: 2.1.5 | C6: 1 | D6: 620 | E6: 5.1.1.2 | F6: Verify users can change their password. | G6: Valid | H6: AccountController.cs:106-145 - Método ChangePassword implementado [HttpPost("change-password")] e [Authorize] para proteger o endpoint | I6: Allowing users to change their passwords is a fundamental security feature that mitigates several threats identified in the DREAD analysis. This capability is crucial in the event of credential compromise, directly relating to high-severity threats such as "Credential interception during transmission" (#10) and "Identity spoofing to gain unauthorized access" (#7). All user types in the AMAP system (Managers, Producers, and Co-Producers) should have this capability to maintain control over their accounts, especially considering the sensitive nature of financial and payment information managed on the platform. | J6: Password change functionality in the user interface Workflows to verify the current password before changing Email notifications for password changes to alert users about unauthorized changes ASP.NET Core Identity for authentication management and password policies
B7: 2.1.6 | C7: 1 | D7: 620 | E7: 5.1.1.2 | F7: Verify that password change functionality requires the user's current and new password. | G7: Valid | H7: ChangePasswordViewModel.cs:6-13 - Campos CurrentPassword e NewPassword obrigatórios AccountController.cs:125 - _userManager.ChangePasswordAsync(user, model.CurrentPassword, model.NewPassword) | I7: Requiring the current password during the password change process is a critical security measure that prevents unauthorized changes in case a session is compromised. This practice protects against several high-severity threats identified in the DREAD analysis, particularly "Privilege escalation from Co-Producer to Producer/Manager" (#18) and "Identity spoofing to gain unauthorized access" (#7). For the AMAP system, where different user profiles have access to different functionalities and sensitive data, this two-step verification is essential to ensure that only the legitimate user can change their password, even if an attacker gains temporary access to the authenticated session. | J7: Password change forms with current password validation Protection against brute force attacks on these interfaces Password change attempt logs for detecting suspicious activities ASP.NET Core Identity for authentication management and password policies
B8: 2.1.7 | C8: 1 | D8: 521 | E8: 5.1.1.2 | F8: Verify that passwords submitted during account registration, login, and password change are checked against a set of breached passwords either locally (such as the top 1,000 or 10,000 most common passwords which match the system's password policy) or using an external API. If using an API a zero knowledge proof or other mechanism should be used to ensure that the plain text password is not sent or used in verifying the breach status of the password. If the password is breached, the application must require the user to set a new non-breached password. ([C6](https://owasp.org/www-project-proactive-controls/#div-numbering)) | G8: Non-valid | I8: Verifying passwords against sets of compromised passwords is a crucial measure to protect against high-severity authentication threats identified in the DREAD analysis. This practice prevents the use of already leaked credentials, significantly reducing the risk of credential stuffing and brute-force attacks related to threats #7 "Identity spoofing to gain unauthorized access" and #9 "Identity spoofing to bypass authentication." For AMAP, where financial transactions and sensitive data from producers and consumers are involved, ensuring that passwords are not compromised is particularly important to protect against attacks that could lead to financial fraud or manipulation of offers. | J8: ASP.NET Core Identity for authentication management and password policies Have I Been Pwned (HIBP) service with k-anonymity implementation Local libraries for checking compromised passwords Zxcvbn or similar libraries for password strength evaluation Password verification APIs with zero-knowledge proof
B9: 2.1.8 | C9: 1 | D9: 521 | E9: 5.1.1.2 | F9: Verify that a password strength meter is provided to help users set a stronger password. | G9: Not Applicable | I9: Implementing a password strength meter provides immediate visual feedback to users, encouraging the creation of stronger and more diverse passwords. This interface feature helps mitigate authentication-related threats identified in the DREAD analysis, such as "Identity spoofing to gain unauthorized access" (#7) and "Identity spoofing to bypass authentication" (#9). For the AMAP system, where different profiles (Managers, Producers, Co-Producers) have access to critical functionalities and sensitive financial data, guiding users in creating strong passwords is essential for the overall security of the platform. | J9: ASP.NET Core Identity for password policies and validation Zxcvbn library for realistic password strength evaluation UI components for password strength meters Real-time feedback with password improvement suggestions
B10: 2.1.9 | C10: 1 | D10: 521 | E10: 5.1.1.2 | F10: Verify that there are no password composition rules limiting the type of characters permitted. There should be no requirement for upper or lower case or numbers or special characters. ([C6](https://owasp.org/www-project-proactive-controls/#div-numbering)) | G10: Non-valid | I10: Avoiding strict password composition rules favors longer and more memorable passwords over complex but short ones, aligning with modern security recommendations from NIST SP 800-63B. This approach helps prevent counterproductive behaviors such as writing down passwords or using predictable patterns. Considering the high-severity authentication-related threats in the DREAD analysis (such as #7 "Identity spoofing to gain unauthorized access" and #9 "Identity spoofing to bypass authentication"), the focus should be on the total entropy of the password, which is better achieved with increased length rather than arbitrary complexity rules. For AMAP, this policy enhances both the security and usability of the system. | J10: Authentication frameworks (like ASP.NET Core Identity) configured to verify only the minimum length Password strength meters based on real entropy (such as zxcvbn) Password policies aligned with NIST recommendations
B11: 2.1.10 | C11: 1 | D11: 263 | E11: 5.1.1.2 | F11: Verify that there are no periodic credential rotation or password history requirements. | G11: Valid | I11: The absence of mandatory periodic password rotation aligns with modern security guidelines (NIST SP 800-63B), which recognize that this practice often leads to risky behaviors such as sequential passwords or password writing. For the AMAP system, it is more effective to focus on detecting compromise (such as anomalous authentication) and provide mechanisms for changing passwords when necessary, rather than forcing arbitrary changes. This approach helps reduce threats identified in the DREAD analysis, such as "Identity spoofing to gain unauthorized access" (#7), without introducing practices that may lower overall security by encouraging weaker or more predictable passwords by users. | J11: Anomalous authentication detection systems Login notifications for new devices/locations Option for users to voluntarily change their passwords using ASP.NET Core Identity
B12: 2.1.11 | C12: 1 | D12: 521 | E12: 5.1.1.2 | F12: Verify that "paste" functionality, browser password helpers, and external password managers are permitted. | G12: Not Applicable | I12: Allowing the ability to paste passwords, browser password helpers, and external password managers is crucial to promote the use of strong and unique passwords. This practice aligns with modern security recommendations (NIST SP 800-63B) and mitigates various high-severity authentication threats identified in the DREAD analysis, such as "Identity spoofing to gain unauthorized access" (#7) and "Credential interception during transmission" (#10). For the AMAP system, with different types of users (Managers, Producers, Co-Producers) who need to keep credentials secure, enabling password manager usage encourages positive security behaviors, reducing the risk of password reuse and weak passwords. | J12: Proper configuration of password fields that do not block the "paste" functionality Support for browser autofill APIs Compatibility with popular password managers, alongside ASP.NET Core Identity
B13: 2.1.12 | C13: 1 | D13: 521 | E13: 5.1.1.2 | F13: Verify that the user can choose to either temporarily view the entire masked password, or temporarily view the last typed character of the password on platforms that do not have this as built-in functionality. | G13: Not Applicable | I13: Allowing temporary password visibility during typing strikes a balance between security and usability. This feature reduces input errors and user frustration while maintaining protection against onlookers ("shoulder surfing"). For AMAP, where different user profiles (Managers, Producers, Co-Producers) access the platform from various environments, this feature is important to avoid unnecessary account lockouts and reduce the tendency to create simple passwords out of fear of typing mistakes. This feature does not significantly compromise security when implemented correctly (temporary visibility, user-activated) and helps balance usability with protections against threats such as "Identity spoofing" (#2, #7, #9). | J13: Modern UI components for password fields with visibility toggle Implementing a timeout to automatically hide the password after brief exposure Visual feedback for the last typed character, in combination with ASP.NET Core Identity
A14: General Authenticator Security - Diogo Costa | B14: 2.2.1 | C14: 1 | D14: 307 | E14: 5.2.2, 5.1.1.2, 5.1.4.2, 5.1.5.2 | F14: Verify that anti-automation controls are effective at mitigating breached credential testing, brute force, and account lockout attacks. Such controls include blocking the most common breached passwords, soft lockouts, rate limiting, CAPTCHA, ever increasing delays between attempts, IP address restrictions, or risk-based restrictions such as location, first login on a device, recent attempts to unlock the account, or similar. Verify that no more than 100 failed attempts per hour is possible on a single account. | G14: Valid | H14: [Authorize] nos controllers | I14: Anti-automation controls are essential to protect against multiple high-severity threats identified in the DREAD analysis, particularly "Identity spoofing to gain unauthorized access" (#7) and "Identity spoofing to bypass authentication" (#9). For AMAP, where unauthorized access could lead to manipulation of listings, identity spoofing of producers or managers, and access to sensitive financial information, implementing defense-in-depth against automated attacks is critical. The combination of different techniques (rate limiting, increasing delays, CAPTCHA, temporary account lockouts) creates multiple barriers against brute force attacks without compromising system availability for legitimate users. | J14: ASP.NET Core Identity (for account lockout and multi-factor authentication) Brute force protection frameworks (like Fail2Ban) CAPTCHA/reCAPTCHA services Anomaly behavior detection systems Rate limiting libraries IP reputation systems Monitoring and alerting for suspicious login attempts
B15: 2.2.2 | C15: 1 | D15: 304 | E15: 5.2.10 | F15: Verify that the use of weak authenticators (such as SMS and email) is limited to secondary verification and transaction approval and not as a replacement for more secure authentication methods. Verify that stronger methods are offered before weak methods, users are aware of the risks, or that proper measures are in place to limit the risks of account compromise. | G15: Non-valid | I15: Limiting weak authenticators (SMS/email) to secondary verifications is crucial for AMAP, considering the high-severity threats identified in the DREAD analysis. This practice protects against "Manager identity spoofing" (#2), "Identity spoofing to gain unauthorized access" (#7), and "Spoofing of AMAP’s email system" (#27). For sensitive operations such as approving financial transactions, creating listings, and managing products, stronger authenticators should be the primary option. This approach is particularly important given AMAP’s system, where different access levels (Managers, Producers, CoProducers) handle sensitive financial and transactional information. | J15: ASP.NET Core Identity (for multi-factor authentication, including TOTP, WebAuthn) Risk analysis systems to determine when additional verification is required User education on risks associated with different authentication methods Authentication frameworks supporting multiple factors with varying levels of security
B16: 2.2.3 | C16: 1 | D16: 620 | F16: Verify that secure notifications are sent to users after updates to authentication details, such as credential resets, email or address changes, logging in from unknown or risky locations. The use of push notifications - rather than SMS or email - is preferred, but in the absence of push notifications, SMS or email is acceptable as long as no sensitive information is disclosed in the notification. | G16: Valid | I16: Secure notifications about changes to authentication details are essential for AMAP, considering several high-severity threats identified in the DREAD analysis, such as "Unauthorized change of payment information" (#17) and "Privilege escalation from CoProducer to Producer/Manager" (#18). For a system that manages financial information and transactions, alerting users about changes to their accounts allows for quick detection of compromise. A preference for push notifications over SMS/email enhances security, but any notification without sensitive data is better than none. This measure also helps mitigate risks related to "Denial of having made a subscription or payment" (#1) by creating visible audit trails for the user. | J16: ASP.NET Core Identity (for event-driven notifications when authentication details are changed) Secure push notification services Anomaly login detection systems Email/SMS templates without sensitive information Logs of sent notifications as part of the audit trail
B17: 2.2.4 | C17: 3 | D17: 308 | E17: 5.2.5 | F17: Verify impersonation resistance against phishing, such as the use of multi-factor authentication, cryptographic devices with intent (such as connected keys with a push to authenticate), or at higher AAL levels, client-side certificates. | G17: Valid | I17: Resistance to impersonation is critical for AMAP, given the multiple high-severity threats related to identity forgery identified in the DREAD analysis: "Impersonation of a Manager" (#2), "Impersonation for unauthorized access" (#7), "Impersonation of a Producer" (#26). For a system that manages financial transactions and allows managers and producers to create offers and manage resources, implementing phishing-resistant authenticators such as physical keys (FIDO2/WebAuthn) or app-based MFA is essential to prevent the compromise of high-privilege accounts. These mechanisms are particularly important for protecting the accounts of Managers and Producers who have extensive privileges in the system. | J17: FIDO2/WebAuthn authenticators (e.g., YubiKeys, Windows Hello) Authentication apps with intent verification (e.g., push to approve) Public Key Infrastructure (PKI) for client certificates Authentication frameworks supporting AAL2/AAL3 level authenticators ASP.NET Core Identity Framework for managing user authentication and integrating with phishing-resistant authenticators
B18: 2.2.5 | C18: 3 | D18: 319 | E18: 5.2.6 | F18: Verify that where a Credential Service Provider (CSP) and the application verifying authentication are separated, mutually authenticated TLS is in place between the two endpoints. | G18: Non-valid | I18: Mutual TLS authentication between the Credential Service Provider (CSP) and the AMAP application is essential to prevent several high-severity threats identified in the DREAD analysis, particularly "Modification of credentials or tokens during transmission" (#8) and "Interception of credentials during transmission" (#10). For a system like AMAP, which handles different access levels and sensitive financial information, ensuring secure and authenticated communication between distributed authentication components is critical. Mutual TLS (mTLS) verifies the identity of both endpoints, preventing man-in-the-middle attacks and ensuring that only authorized services can participate in the authentication flow. | J18: Public Key Infrastructure (PKI) for certificate management API Gateways with mTLS support Secure reverse proxies (e.g., Nginx, HAProxy) configured for mTLS Monitoring systems for certificate validity verification
B19: 2.2.6 | C19: 3 | D19: 308 | E19: 5.2.8 | F19: Verify replay resistance through the mandated use of One-time Passwords (OTP) devices, cryptographic authenticators, or lookup codes. | G19: Non-valid | I19: Resistance to replay attacks is essential for AMAP, considering the high-severity threats identified in the DREAD analysis, particularly "Impersonation for unauthorized access" (#7) and "Modification of credentials or tokens during transmission" (#8). To protect sensitive operations like payments, data modifications, and offer creation, implementing authenticators that generate one-time-use tokens (TOTP/HOTP) or cryptographic challenges prevents the reuse of captured credentials. This measure is especially important for Manager and Producer accounts that have privileged access in the system, mitigating the risk of session compromise or credential interception. | J19: TOTP/HOTP authentication apps (e.g., Google Authenticator, Microsoft Authenticator) FIDO2/WebAuthn authenticators with cryptographic challenges One-time code generation and verification systems Authentication frameworks supporting ephemeral tokens
B20: 2.2.7 | C20: 3 | D20: 308 | E20: 5.2.9 | F20: Verify intent to authenticate by requiring the entry of an OTP token or user-initiated action such as a button press on a FIDO hardware key. | G20: Non-valid | I20: Authentication intent verification is crucial for AMAP, considering multiple high-severity threats in the DREAD analysis, such as "Impersonation for unauthorized access" (8.0), "Impersonation to bypass authentication" (7.8), and "Credential interception during transmission" (7.8). Requiring an explicit user action (such as pressing a button on a FIDO key) or entering an OTP token confirms that the authentication is intentional and not automated by malware. This additional layer of protection is particularly important for Managers and Producers who have privileged access to critical system functions, such as payment and offer management. In addition to mitigating phishing risks, this requirement also helps fulfill GDPR obligations related to the protection of personal data. | J20: FIDO2/WebAuthn authenticators (e.g., YubiKey, security keys) TOTP authentication apps (e.g., Google Authenticator, Microsoft Authenticator) Authentication frameworks supporting MFA (e.g., Auth0, Firebase Authentication) WebAuthn integration libraries for web platforms
A21: Authenticator Lifecycle | B21: 2.3.1 | C21: 1 | D21: 330 | E21: 5.1.1.2, A. 3 | F21: Verify system generated initial passwords or activation codes SHOULD be securely randomly generated, SHOULD be at least 6 characters long, and MAY contain letters and numbers, and expire after a short period of time. These initial secrets must not be permitted to become the long term password. | G21: Not Applicable | I21: The implementation of initial passwords or activation codes generated by the system with secure characteristics is essential for AMAP, mitigating several high-severity threats from the DREAD analysis, such as "Impersonation of a Manager" (8.0) and "Impersonation for unauthorized access" (8.0). Ensuring that these temporary credentials are random, sufficiently complex, and expire quickly significantly reduces the window of opportunity for attacks during the registration or password reset process. Requiring users to change these initial passwords to permanent credentials chosen by the user is crucial to prevent unauthorized access, especially considering that privileged roles in the system (Managers and Producers) could be compromised. This practice also aligns with GDPR requirements to implement appropriate technical measures to protect personal data. | J21: Cryptographically Secure Pseudo-Random Number Generators (CSPRNG) Authentication frameworks supporting temporary passwords (e.g., ASP.NET Identity) Systems for automatic expiration of temporary passwords Password policy verification modules
B22: 2.3.2 | C22: 2 | D22: 308 | E22: 6.1.3 | F22: Verify that enrollment and use of user-provided authentication devices are supported, such as a U2F or FIDO tokens. | G22: Non-valid | I22: Supporting the integration and use of user-provided authentication devices, such as FIDO/U2F tokens, is highly relevant for AMAP due to several high-severity threats identified in the DREAD analysis, particularly "Impersonation for unauthorized access" (8.0), "Impersonation of a Manager" (8.0), and "Credential interception during transmission" (7.8). Physical security keys provide superior protection against phishing and credential theft attacks, as authentication depends on the possession of a physical device rather than credentials that can be compromised. For privileged roles like Managers and Producers, who have access to sensitive financial information and can modify offers or process payments, this additional layer of security is particularly valuable. Additionally, this requirement aligns with modern security recommendations and facilitates compliance with GDPR by implementing appropriate technical measures to protect personal data. | J22: WebAuthn/FIDO2 libraries (e.g., SimpleWebAuthn) FIDO security devices (e.g., YubiKey, Google Titan, etc.) Authentication frameworks supporting FIDO/U2F Credential management APIs for token registration and verification SDKs for integration with identity providers supporting FIDO ASP.NET Identity for user management and MFA integration (Note: ASP.NET Identity needs to be integrated with FIDO2/WebAuthn libraries for full support of FIDO/U2F tokens)
B23: 2.3.3 | C23: 2 | D23: 287 | E23: 6.1.4 | F23: Verify that renewal instructions are sent with sufficient time to renew time bound authenticators. | G23: Non-valid | I23: Ensuring that renewal instructions are sent in advance is essential for AMAP, especially to mitigate risks related to loss of access due to expired authentications. This is relevant to threats identified in the DREAD analysis, such as "Impersonation to bypass authentication" (7.8) and "Unauthorized access to control functionalities" (7.2). Timely renewal of temporal authenticators, such as tokens or certificates, reduces the risk of interruptions in legitimate access and prevents users from resorting to insecure practices like reusing compromised credentials. This practice also improves the user experience and aligns with security best practices, ensuring the continuity of strong authentication usage. | J23: Automated notification systems (email, SMS, push notifications) Authentication management APIs with token renewal support Certificate/authenticator expiration monitoring tools Authentication frameworks with support for renewal reminders (e.g., Auth0, Okta) ASP.NET Identity for managing authentication expiration and session renewal
A24: Credentials Storage - Pedro Costa | B24: 2.4.1 | C24: 2 | D24: 916 | E24: 5.1.1.2 | F24: Verify that passwords are stored in a form that is resistant to offline attacks. Passwords SHALL be salted and hashed using an approved one-way key derivation or password hashing function. Key derivation and password hashing functions take a password, a salt, and a cost factor as inputs when generating a password hash. ([C6](https://owasp.org/www-project-proactive-controls/#div-numbering)) | G24: Valid | H24: The Identity configuration is done in Program.cs, "builder.Services.AddIdentity<AppUser, IdentityRole>() .AddEntityFrameworkStores<AppDbContext>() .AddDefaultTokenProviders();" and the AppUser inherits from IdentityUser, that includes all the fields for a secure management of passwords. | I24: Storing passwords securely is essential for AMAP, considering threats such as "Credential interception during transmission" (7.8) and "Access to sensitive user information" (7.8). The use of approved key derivation or hashing functions, such as bcrypt, Argon2, or PBKDF2, with salting and a cost factor, protects against offline attacks, such as brute force or dictionary attacks, even if the hashes are compromised. This practice is crucial for protecting user accounts, especially those with elevated privileges, such as Managers and Producers. Additionally, secure password storage is a requirement under the GDPR to protect personal data and aligns with best security practices recommended by OWASP. | J24: Password hashing libraries (bcrypt, Argon2, PBKDF2) Authentication frameworks with support for secure hashing (ASP.NET Identity) Auditing tools to verify the security of password storage Security policy configuration for passwords (e.g., minimum length, complexity)
B25: 2.4.2 | C25: 2 | D25: 916 | E25: 5.1.1.2 | F25: Verify that the salt is at least 32 bits in length and be chosen arbitrarily to minimize salt value collisions among stored hashes. For each credential, a unique salt value and the resulting hash SHALL be stored. ([C6](https://owasp.org/www-project-proactive-controls/#div-numbering)) | G25: Valid | H25: In Program.cs we have "// Configure password hasher with explicit salt size and security parameters builder.Services.Configure<PasswordHasherOptions>(options => { // Salt size is 128 bits (16 bytes) - exceeds OWASP requirement of minimum 32 bits // Each user gets a unique random salt to prevent salt collisions options.IterationCount = 100000; // OWASP C6: PBKDF2 iteration count set to 100,000 as recommended options.CompatibilityMode = PasswordHasherCompatibilityMode.IdentityV3; // Uses PBKDF2 with HMAC-SHA256 });", that uses PasswordHasherCompatibilityMode, that specifies the format used for hashing passwords. | I25: Using a unique and random salt of at least 32 bits in length is essential for protecting passwords stored in AMAP against offline attacks, such as brute force and rainbow table attacks. This practice mitigates threats identified in the DREAD analysis, such as "Access to sensitive user information" (7.8) and "Credential interception during transmission" (7.8). A unique salt per credential ensures that identical hashes are not generated for the same passwords, even if they are used by different users. This approach aligns with best security practices and GDPR requirements for protecting personal data. | J25: Password hashing libraries with support for salting (bcrypt, Argon2, PBKDF2) Cryptographically secure random number generators (CSPRNG) for generating salt Authentication frameworks that implement automatic salting (e.g., ASP.NET Identity) Auditing tools to verify the uniqueness and length of stored salts
B26: 2.4.3 | C26: 2 | D26: 916 | E26: 5.1.1.2 | F26: Verify that if PBKDF2 is used, the iteration count SHOULD be as large as verification server performance will allow, typically at least 100,000 iterations. ([C6](https://owasp.org/www-project-proactive-controls/#div-numbering)) | G26: Valid | H26: In Program.cs we have "// Configure password hasher with explicit salt size and security parameters builder.Services.Configure<PasswordHasherOptions>(options => { // Salt size is 128 bits (16 bytes) - exceeds OWASP requirement of minimum 32 bits // Each user gets a unique random salt to prevent salt collisions options.IterationCount = 100000; // OWASP C6: PBKDF2 iteration count set to 100,000 as recommended options.CompatibilityMode = PasswordHasherCompatibilityMode.IdentityV3; // Uses PBKDF2 with HMAC-SHA256 });", and this code shows the implementation of PBKDF2 (through Identity), the iteration count of 100000 as recommended by OWASP and the explicit documentation of the security parameters. | I26: Using a high number of iterations in PBKDF2 is essential to increase resistance against offline attacks, such as brute force, by making the hashing process computationally expensive for attackers. This requirement is relevant for AMAP, considering threats such as "Access to sensitive user information" (7.8) and "Credential interception during transmission" (7.8). A minimum of 100,000 iterations is recommended, but the exact number should balance security and the performance of the authentication server. This practice aligns with best security practices and helps meet GDPR requirements for protecting personal data. | J26: Authentication frameworks that support configurable PBKDF2 (e.g., ASP.NET Identity) Benchmark tools to determine the ideal number of iterations based on server performance Regular audits to ensure the iteration count is up-to-date with current security standards
B27: 2.4.4 | C27: 2 | D27: 916 | E27: 5.1.1.2 | F27: Verify that if bcrypt is used, the work factor SHOULD be as large as verification server performance will allow, with a minimum of 10. ([C6](https://owasp.org/www-project-proactive-controls/#div-numbering)) | G27: Not Applicable | H27: Our current PBKDF2 implementation already meets all these requirements, so we don't need to switch to bcrypt. | I27: Using a high work factor in bcrypt is essential to increase resistance against offline attacks, such as brute force, by making the hashing process slower and computationally expensive for attackers. This requirement is relevant for AMAP, considering threats such as "Access to sensitive user information" (7.8) and "Credential interception during transmission" (7.8). A minimum work factor of 10 is recommended, but it should be adjusted based on server performance to ensure a balance between security and usability. This practice aligns with best security practices and helps protect personal data, in compliance with GDPR. | J27: Authentication frameworks that support configurable bcrypt (e.g., ASP.NET Identity) Benchmark tools to determine the ideal work factor based on server performance Regular audits to ensure the work factor is up-to-date with current security standards
B28: 2.4.5 | C28: 2 | D28: 916 | E28: 5.1.1.2 | F28: Verify that an additional iteration of a key derivation function is performed, using a salt value that is secret and known only to the verifier. Generate the salt value using an approved random bit generator [SP 800-90Ar1] and provide at least the minimum security strength specified in the latest revision of SP 800-131A. The secret salt value SHALL be stored separately from the hashed passwords (e.g., in a specialized device like a hardware security module). | G28: Valid | I28: Performing an additional iteration of a key derivation function with a secret salt significantly improves security against offline attacks, even if password hashes are compromised. This requirement is relevant for AMAP, considering threats such as "Access to sensitive user information" (7.8) and "Credential interception during transmission" (7.8). The use of a secret salt, generated by an approved cryptographically secure random number generator (SP 800-90Ar1), and stored separately (such as in an HSM), adds an extra layer of protection, making brute force and targeted attacks more difficult. This practice aligns with modern security standards and helps comply with GDPR requirements for protecting personal data. | J28: Cryptographically secure random number generators (CSPRNGs) compliant with SP 800-90Ar1 Hardware Security Modules (HSMs) for secure storage of secret salts Key derivation function implementations (e.g., Argon2, PBKDF2, bcrypt) with support for multiple iterations Authentication frameworks that allow configuration of secret salts and secure storage (e.g., AWS KMS, Azure Key Vault)
A29: Credential Recovery - Pedro Costa | B29: 2.5.1 | C29: 1 | D29: 640 | E29: 5.1.1.2 | F29: Verify that a system generated initial activation or recovery secret is not sent in clear text to the user. ([C6](https://owasp.org/www-project-proactive-controls/#div-numbering)) | G29: Non-valid | I29: Sending activation or recovery secrets in clear text exposes the system to significant risks, such as "Credential interception during transmission" (7.8) and "Unauthorized exposure of sensitive data" (7.6), identified in the AMAP DREAD analysis. To protect these secrets, it is essential to transmit them securely, using encrypted channels (such as HTTPS or TLS for emails) or alternative methods like one-time-use links or codes sent via authenticated apps. This practice reduces the risk of interception by attackers and aligns with the GDPR requirements to protect personal data during transmission. | J29: Secure communication protocols (TLS 1.2 or higher) Email sending APIs with encryption support (e.g., AWS SES, SendGrid) Authentication apps for secret delivery (e.g., Google Authenticator, Microsoft Authenticator Authentication frameworks supporting one-time-use links or tokens (e.g., Auth0, Firebase Authentication) ASP.NET Identity (for secure management of authentication and password recovery)
B30: 2.5.2 | C30: 1 | D30: 640 | E30: 5.1.1.2 | F30: Verify password hints or knowledge-based authentication (so-called "secret questions") are not present. | G30: Valid | H30: This requirement is satisfied, because there are no password hints or knowledge-based authentication (secret questions) implemented in the system. | I30: The use of password hints or knowledge-based questions ("secret questions") is widely considered insecure, as these practices are vulnerable to social engineering attacks and the collection of public information. In the context of AMAP, this helps mitigate threats such as "Identity spoofing for unauthorized access" (8.0) and "Access to sensitive user information" (7.8). Replacing these practices with more secure methods, such as multifactor authentication (MFA) or password recovery links sent via secure channels, significantly improves system security and aligns with best practices recommended by OWASP and GDPR requirements | J30: Authentication frameworks that do not use security questions (e.g., Auth0, Firebase Authentication) MFA implementation (e.g., TOTP, FIDO2) Secure password recovery APIs with one-time-use links (e.g., AWS Cognito, Okta) ASP.NET Identity (supports MFA and secure password recovery via secure links)
B31: 2.5.3 | C31: 1 | D31: 640 | E31: 5.1.1.2 | F31: Verify password credential recovery does not reveal the current password in any way. ([C6](https://owasp.org/www-project-proactive-controls/#div-numbering)) | G31: Valid | H31: We have Password Recovery Flow in AccountController.cs: // Step 1: Request Password Reset [HttpPost("forgot-password")] public async Task<IActionResult> ForgotPassword([FromBody] ForgotPasswordViewModel model) { // Generate token only for existing users var token = await _userManager.GeneratePasswordResetTokenAsync(user); } // Step 2: Reset Password [HttpPost("reset-password")] public async Task<IActionResult> ResetPassword([FromBody] ResetPasswordViewModel model) { // Verify token and reset password var isValid = await _userManager.VerifyUserTokenAsync(user, ...); var result = await _userManager.ResetPasswordAsync(user, model.Token, model.NewPassword); } | I31: Ensuring that the password recovery process does not reveal the current password is essential to protect AMAP users from threats such as "Access to sensitive user information" (7.8) and "Unauthorized exposure of sensitive data" (7.6). Displaying or sending the current password compromises security, especially if the credentials are intercepted or viewed by third parties. Instead, the system should allow secure password resets using one-time-use links or temporary codes sent via secure channels. This practice aligns with security best practices and GDPR requirements to protect personal data. | J31: Secure password reset APIs (e.g., AWS Cognito, Firebase Authentication) Implementation of one-time-use password reset links Authentication frameworks that support password recovery without exposing the current password (e.g., Auth0, Okta) ASP.NET Identity (supports secure password reset with no exposure of current password) Secure communication protocols (TLS 1.2 or higher) for sending reset instructions
B32: 2.5.4 | C32: 1 | D32: 16 | E32: 5.1.1.2, A. 3 | F32: Verify shared or default accounts are not present (e.g. "root", "admin", or "sa"). | G32: Valid | H32: This requirement is done, we had Bootstrap Accounts with the default names, that are removed for safer architecture. | I32: The presence of shared or default accounts, such as "root", "admin", or "sa", represents a significant risk for AMAP, as it facilitates attacks such as "Privilege escalation from CoProducer to Producer/Manager" (7.6) and "Unauthorized access to control features" (7.2). These accounts are often targets for brute force attacks or exploitation of default credentials. To mitigate these risks, it is essential to disable or remove default accounts and ensure that each user has unique, traceable credentials. This practice aligns with security best practices and helps comply with GDPR requirements for protecting personal data and ensuring accountability in access. | J32: Identity and Access Management (IAM) tools to disable default accounts Regular system account and permission audits Authentication frameworks that require unique credentials for each user (e.g., Keycloak, Okta) ASP.NET Identity (supports the enforcement of unique credentials for each user) Security policies prohibiting the use of shared accounts
B33: 2.5.5 | C33: 1 | D33: 304 | E33: 6.1.2.3 | F33: Verify that if an authentication factor is changed or replaced, that the user is notified of this event. | G33: Valid | H33: TwoFactorAuthController.cs: SendCredentialsChangeNotificationAsync() | I33: Notifying users when an authentication factor is changed or replaced is essential to protect AMAP against threats like "Identity spoofing for unauthorized access" (8.0) and "Privilege escalation from CoProducer to Producer/Manager" (7.6). This practice allows users to detect unauthorized activities in their accounts and take immediate action, such as blocking access or resetting credentials. The notification should be sent through a secure and reliable channel, such as email or SMS, and include sufficient information for the user to recognize the action without exposing sensitive details. This measure aligns with security best practices and the GDPR requirements to protect personal data. | J33: Secure notification APIs (e.g., Twilio, AWS SNS, SendGrid) Authentication frameworks with support for notification events (e.g., Auth0, Firebase Authentication, ASP.NET Identity) Audit logs to track authentication factor changes Secure communication protocols (TLS 1.2 or higher) for sending notifications
B34: 2.5.6 | C34: 1 | D34: 640 | E34: 5.1.1.2 | F34: Verify forgotten password, and other recovery paths use a secure recovery mechanism, such as time-based OTP (TOTP) or other soft token, mobile push, or another offline recovery mechanism. ([C6](https://owasp.org/www-project-proactive-controls/#div-numbering)) | G34: Non-valid | I34: The use of secure password recovery mechanisms, such as TOTP, software tokens, push notifications, or offline methods, is essential to protect AMAP against threats like "Identity spoofing for unauthorized access" (8.0) and "Credentials interception during transmission" (7.8). These methods ensure that only the legitimate user can regain access to the account, even if other channels are compromised. Additionally, they prevent the exposure of sensitive information during the recovery process. This practice aligns with security best practices and GDPR requirements to protect personal data. | J34: TOTP implementations (e.g., Google Authenticator, Microsoft Authenticator) Secure push notification APIs (e.g., Firebase Cloud Messaging, OneSignal) Authentication frameworks with support for secure recovery (e.g., Auth0, Okta, ASP.NET Identity) Secure communication protocols (TLS 1.2 or higher) for sending recovery codes or links
B35: 2.5.7 | C35: 2 | D35: 308 | E35: 6.1.2.3 | F35: Verify that if OTP or multi-factor authentication factors are lost, that evidence of identity proofing is performed at the same level as during enrollment. | G35: Non-valid | H35: TwoFactorAuthController.cs: ValidateToken() | I35: Ensuring that identity proofing is conducted at the same level as the initial enrollment process when recovering lost authentication factors is essential to protect AMAP against threats like "Identity spoofing for unauthorized access" (8.0) and "Privilege escalation from CoProducer to Producer/Manager" (7.6). This requirement prevents attackers from exploiting recovery processes to gain unauthorized access. The user's identity should be verified using secure methods, such as document validation, biometric verification, or other trusted factors, ensuring that the security level remains consistent. This practice aligns with security best practices and GDPR requirements to protect personal data. | J35: Identity verification APIs (e.g., Onfido, Jumio) Authentication frameworks with support for secure recovery (e.g., Auth0, Okta, ASP.NET Identity) Biometric verification methods (e.g., facial recognition, fingerprinting) Audit logs to track and validate recovery processes
A36: Look-up Secret Verifier | B36: 2.6.1 | C36: 2 | D36: 308 | E36: 5.1.2.2 | F36: Verify that lookup secrets can be used only once. | G36: Valid | H36: TwoFactorAuthController.cs: TOTP implementation | I36: Ensuring that lookup secrets are one-time use is essential to protect AMAP against reuse attacks, such as "Identity spoofing for unauthorized access" (8.0) and "Interception of credentials during transmission" (7.8). One-time use lookup secrets, like recovery codes or OTPs, prevent an attacker from reusing compromised credentials. After use, the secret should be immediately invalidated to ensure it cannot be exploited again. This practice aligns with security best practices and helps comply with GDPR requirements for protecting personal data. | J36: OTP implementations based on TOTP or HOTP (e.g., Google Authenticator, Microsoft Authenticator) Authentication frameworks that support one-time use codes (e.g., Auth0, Firebase Authentication, ASP.NET Identity) Token management systems with support for invalidation after use Audit logs to monitor and validate the use of lookup secrets
B37: 2.6.2 | C37: 2 | D37: 330 | E37: 5.1.2.2 | F37: Verify that lookup secrets have sufficient randomness (112 bits of entropy), or if less than 112 bits of entropy, salted with a unique and random 32-bit salt and hashed with an approved one-way hash. | G37: Non-valid | I37: Ensuring that lookup secrets are one-time use is essential to protect AMAP against reuse attacks, such as "Identity spoofing for unauthorized access" (8.0) and "Interception of credentials during transmission" (7.8). One-time use lookup secrets, like recovery codes or OTPs, prevent an attacker from reusing compromised credentials. After use, the secret should be immediately invalidated to ensure it cannot be exploited again. This practice aligns with security best practices and helps comply with GDPR requirements for protecting personal data. | J37: OTP implementations based on TOTP or HOTP (e.g., Google Authenticator, Microsoft Authenticator) Authentication frameworks that support one-time use codes (e.g., Auth0, Firebase Authentication, ASP.NET Identity) Token management systems with support for invalidation after use Audit logs to monitor and validate the use of lookup secrets
B38: 2.6.3 | C38: 2 | D38: 310 | E38: 5.1.2.2 | F38: Verify that lookup secrets are resistant to offline attacks, such as predictable values. | G38: Non-valid | I38: Ensuring that lookup secrets are resistant to offline attacks, such as predictable values, is essential to protect AMAP against threats like "Interception of credentials during transmission" (7.8) and "Access to sensitive user information" (7.8). Lookup secrets should be generated cryptographically securely, using approved random number generators, to prevent attackers from predicting or guessing the values. Additionally, secrets should be stored securely using hashing with salting, to make brute force attacks more difficult in case they are compromised. This practice aligns with security best practices and GDPR requirements for protecting personal data. | J38: Cryptographically secure random number generators (CSPRNG) to create unpredictable secrets Approved hashing libraries (e.g., Argon2, bcrypt, SHA-256 with salting) Authentication frameworks that support secure generation and storage of secrets (e.g., Auth0, Firebase Authentication, ASP.NET Identity) Regular audits to verify the unpredictability and security of lookup secrets
A39: Out of Band Verifier | B39: 2.7.1 | C39: 1 | D39: 287 | E39: 5.1.3.2 | F39: Verify that clear text out of band (NIST "restricted") authenticators, such as SMS or PSTN, are not offered by default, and stronger alternatives such as push notifications are offered first. | G39: Non-valid | I39: Avoiding the use of out-of-band authenticators in plain text, such as SMS or PSTN, by default is crucial to protect the AMAP from threats like "Credential interception during transmission" (7.8) and "Identity spoofing for unauthorized access" (8.0). These methods are vulnerable to attacks such as SIM swapping and message interception. Safer alternatives, like authenticated push notifications or TOTP, should be prioritized to ensure better protection. This practice aligns with NIST recommendations and security best practices, in addition to helping comply with GDPR requirements to protect personal data. | J39: Secure push notification APIs (e.g., Firebase Cloud Messaging, OneSignal) TOTP implementations (e.g., Google Authenticator, Microsoft Authenticator) Authentication frameworks that prioritize secure methods (e.g., Auth0, Okta, ASP.NET Core Identity) Regular audits to ensure insecure methods are not configured as defaults
B40: 2.7.2 | C40: 1 | D40: 287 | E40: 5.1.3.2 | F40: Verify that the out of band verifier expires out of band authentication requests, codes, or tokens after 10 minutes. | G40: Non-valid | I40: Ensuring that out-of-band verifiers expire requests, codes, or tokens after 10 minutes is essential to protect AMAP against threats like "Credential interception during transmission" (7.8) and "Identity spoofing to gain unauthorized access" (8.0). Limiting the validity period reduces the opportunity window for attackers to exploit compromised or intercepted codes. Additionally, this practice enhances the overall security of the system by minimizing the impact of exposed temporary credentials. It aligns with best security practices and the GDPR requirements to protect personal data. | J40: Authentication frameworks supporting token expiration (e.g., Auth0, Firebase Authentication, ASP.NET Core Identity) Token management APIs with configurable expiration times (e.g., OAuth2, JWT) Regular audits to check compliance with configured expiration times Audit logs to monitor the usage and expiration of codes or tokens
B41: 2.7.3 | C41: 1 | D41: 287 | E41: 5.1.3.2 | F41: Verify that the out of band verifier authentication requests, codes, or tokens are only usable once, and only for the original authentication request. | G41: Valid | H41: Password reset tokens: AccountController.cs — uso único via ResetPasswordAsync e VerifyUserTokenAsync (ASP.NET Identity). MFA TOTP: TwoFactorAuthController.cs — uso único via ValidateTwoFactorPIN (TOTP). | I41: Ensuring that out-of-band authentication requests, codes, or tokens are single-use and linked to the original request is essential to protect AMAP against reuse attacks, such as "Identity spoofing to gain unauthorized access" (8.0) and "Credential interception during transmission" (7.8). Reusable tokens or tokens that are not linked to the original request can be exploited by attackers to gain unauthorized access. Implementing verifiers that automatically invalidate tokens after use or expiration ensures greater security. This practice aligns with best security practices and GDPR requirements for protecting personal data. | J41: Authentication frameworks that support one-time use tokens (e.g., Auth0, Firebase Authentication, ASP.NET Identity) Token management APIs with context binding support (e.g., OAuth2, JWT, ASP.NET Identity) Audit logs to track and validate token usage Implementation of verifiers that invalidate tokens after use or expiration (e.g., ASP.NET Identity)s
B42: 2.7.4 | C42: 1 | D42: 523 | E42: 5.1.3.2 | F42: Verify that the out of band authenticator and verifier communicates over a secure independent channel. | G42: Non-valid | I42: Ensuring that the out-of-band authenticator and verifier communicate over a secure and independent channel is essential to protect the AMAP from threats like "Credential interception during transmission" (7.8) and "Identity spoofing to gain unauthorized access" (8.0). An independent and secure channel, such as authenticated push notifications or dedicated apps, reduces the risk of interception or manipulation of data by attackers. Additionally, using secure protocols, such as TLS, ensures the confidentiality and integrity of communication. This practice aligns with best security practices and GDPR requirements to protect personal data. | J42: Secure push notification APIs (e.g., Firebase Cloud Messaging, OneSignal) Independent channel implementations, such as authenticator apps (e.g., Google Authenticator, Microsoft Authenticator) Secure communication protocols (TLS 1.2 or higher) Regular audits to verify the security of the communication channels used ASP.NET Identity for secure authentication and user credential management
B43: 2.7.5 | C43: 2 | D43: 256 | E43: 5.1.3.2 | F43: Verify that the out of band verifier retains only a hashed version of the authentication code. | G43: Non-valid | I43: Storing only a hashed version of the out-of-band authentication code is essential to protect the AMAP from attacks such as "Access to sensitive user information" (7.8) and "Credential interception during transmission" (7.8). This ensures that even if storage is compromised, the original codes cannot be retrieved or reused. The hash should be generated using a secure, approved hashing function such as SHA-256 and ideally combined with a unique salt for added protection. This practice aligns with best security practices and GDPR requirements to protect personal data. | J43: Secure hashing libraries (e.g., bcrypt, Argon2, SHA-256 with salting) Authentication frameworks that support secure storage of codes (e.g., Auth0, Firebase Authentication) Regular audits to ensure only hashed codes are stored Audit logs to monitor the use and validity of hashed codes ASP.NET Identity for secure storage and management of authentication codes
B44: 2.7.6 | C44: 2 | D44: 310 | E44: 5.1.3.2 | F44: Verify that the initial authentication code is generated by a secure random number generator, containing at least 20 bits of entropy (typically a six digital random number is sufficient). | G44: Non-valid | I44: Ensuring that the initial authentication code is generated by a cryptographically secure random number generator (CSPRNG) with at least 20 bits of entropy is essential to protect the AMAP from attacks such as "Identity spoofing to gain unauthorized access" (8.0) and "Credential interception during transmission" (7.8). A code with 20 bits of entropy (such as a six-digit random number) is sufficiently unpredictable to resist brute-force attacks. This practice aligns with best security practices and GDPR requirements to protect personal data. | J44: Cryptographically secure random number generators (CSPRNG) (e.g., System.Security.Cryptography.RandomNumberGenerator in .NET) Authentication frameworks that support secure code generation (e.g., Auth0, Firebase Authentication) Regular audits to verify the entropy and security of generated codes Audit logs to monitor the use and validity of authentication codes ASP.NET Identity for securely generating and managing authentication codes
A45: One Time Verifier | B45: 2.8.1 | C45: 1 | D45: 613 | E45: 5.1.4.2, 5.1.5.2 | F45: Verify that time-based OTPs have a defined lifetime before expiring. | G45: Not Applicable | I45: Ensuring that time-based one-time passwords (TOTP) have a defined lifespan before expiration is essential to protect the AMAP from attacks such as "Credential interception during transmission" (7.8) and "Identity spoofing to gain unauthorized access" (8.0). A short lifespan (typically 30 seconds) reduces the opportunity for an attacker to use an intercepted code. This practice improves the overall security of the system and aligns with best security practices and GDPR requirements to protect personal data. | J45: TOTP implementations (e.g., Google Authenticator, Microsoft Authenticator) Authentication frameworks that support TOTP with expiration time configuration (e.g., Auth0, Okta) Regular audits to verify compliance with configured expiration times ASP.NET Identity for managing and configuring TOTP expiration times securely
B46: 2.8.2 | C46: 2 | D46: 320 | E46: 5.1.4.2, 5.1.5.2 | F46: Verify that symmetric keys used to verify submitted OTPs are highly protected, such as by using a hardware security module or secure operating system based key storage. | G46: Non-valid | I46: Protecting the symmetric keys used to verify OTPs is essential to avoid compromises that could lead to attacks such as "Identity spoofing to gain unauthorized access" (8.0) and "Co-Producer privilege escalation to Producer/Manager" (7.6). The use of hardware security modules (HSMs) or OS-based secure storage (such as Windows DPAPI or Android Keystore) ensures that keys remain inaccessible to attackers, even in the event of a partial system compromise. This practice aligns with best security practices and GDPR requirements to protect sensitive data. | J46: Hardware Security Modules (HSMs) (e.g., AWS CloudHSM, Azure Key Vault HSM) OS-based secure storage (e.g., Windows DPAPI, Android Keystore, Apple Secure Enclave) Authentication frameworks that support secure key management (e.g., Auth0, Firebase Authentication) Regular audits to verify the protection and secure management of symmetric keys ASP.NET Identity for securely managing OTP verification keys
B47: 2.8.3 | C47: 2 | D47: 326 | E47: 5.1.4.2, 5.1.5.2 | F47: Verify that approved cryptographic algorithms are used in the generation, seeding, and verification of OTPs. | G47: Non-valid | I47: The use of approved cryptographic algorithms for the generation, initialization (seeding), and verification of OTPs is essential to protect the AMAP against attacks such as "Credential interception during transmission" (7.8) and "Identity spoofing to gain unauthorized access" (8.0). Algorithms like HMAC-SHA1, HMAC-SHA256, or HMAC-SHA512, as specified in RFC 6238 (for TOTP) and RFC 4226 (for HOTP), ensure the security and integrity of OTPs. Using unapproved or insecure algorithms could compromise the system's resistance to attacks. This practice aligns with best security practices and GDPR requirements to protect personal data. | J47: Authentication frameworks that support approved cryptographic algorithms (e.g., Auth0, Okta) Regular audits to verify compliance with approved cryptographic algorithms Security analysis tools to validate the implementation of cryptographic algorithms ASP.NET Identity for implementing secure OTP generation and verification algorithms
B48: 2.8.4 | C48: 2 | D48: 287 | E48: 5.1.4.2, 5.1.5.2 | F48: Verify that time-based OTP can be used only once within the validity period. | G48: Non-valid | I48: Ensuring that time-based OTPs (TOTP) can only be used once within their validity period is essential to protect the AMAP against reuse attacks, such as "Identity spoofing to gain unauthorized access" (8.0) and "Credential interception during transmission" (7.8). Even if an attacker intercepts a valid OTP, the restriction of one-time use prevents it from being reused to compromise the account. This practice enhances the overall security of the system and aligns with best security practices and GDPR requirements to protect personal data. | J48: Authentication frameworks that support single-use control for TOTP (e.g., Auth0, Firebase Authentication) Audit logs to monitor and validate the one-time use of OTPs Token management systems that invalidate OTPs after use ASP.NET Identity for managing secure OTP usage and validation
B49: 2.8.5 | C49: 2 | D49: 287 | E49: 5.1.5.2 | F49: Verify that if a time-based multi-factor OTP token is re-used during the validity period, it is logged and rejected with secure notifications being sent to the holder of the device. | G49: Non-valid | H49: TOTP can be reused during its validity period; there is no rejection, logging, or notification (TwoFactorAuthController.cs). Standard TOTP verification is implemented, allowing any valid code within the time window to be accepted. There is no mechanism to detect or prevent code reuse within the same period. | I49: Ensuring that the reuse of a time-based OTP (TOTP) within its validity period is logged, rejected, and notified to the device holder is essential to protect the AMAP against reuse attacks, such as "Identity spoofing to gain unauthorized access" (8.0). Logging the event allows for audits and investigations, while rejecting the token prevents unauthorized access. Notifying the user securely (via email or push notification) raises awareness of potential attack attempts and enables immediate corrective actions. This practice aligns with best security practices and GDPR requirements to protect personal data. | J49: Authentication frameworks that support rejection and logging of OTP reuse (e.g., Auth0, Firebase Authentication) Secure notification APIs (e.g., Twilio, Firebase Cloud Messaging) Audit logs to monitor OTP reuse attempts Secure communication protocols (TLS 1.2 or higher) for sending notifications ASP.NET Identity for managing OTP reuse prevention, logging, and notifications
B50: 2.8.6 | C50: 2 | D50: 613 | E50: 5.2.1 | F50: Verify physical single-factor OTP generator can be revoked in case of theft or other loss. Ensure that revocation is immediately effective across logged in sessions, regardless of location. | G50: Non-valid | I50: Ensuring that physical one-factor OTP generators can be revoked in case of theft or loss is essential to protect the AMAP from unauthorized access, mitigating threats such as "Identity spoofing to gain unauthorized access" (8.0). Immediate revocation, effective across all active sessions, prevents the compromised device from being used for authentication, regardless of its location. This requirement enhances the overall security of the system and aligns with best security practices and GDPR requirements to protect personal data. | J50: Authentication device management systems (e.g., Okta, Auth0) Token and session revocation APIs (e.g., OAuth2, OpenID Connect) Audit logs to track revocations and subsequent access Authentication frameworks supporting immediate device revocation (e.g., Firebase Authentication, Keycloak) ASP.NET Identity for managing device revocation and ensuring session invalidation
B51: 2.8.7 | C51: 3 | D51: 308 | E51: 5.2.3 | F51: Verify that biometric authenticators are limited to use only as secondary factors in conjunction with either something you have and something you know. | G51: Non-valid | I51: Ensuring that biometric authenticators are used only as secondary factors, combined with something the user possesses (e.g., physical device) and something they know (e.g., password), is essential to protect the AMAP against attacks such as "Identity spoofing to gain unauthorized access" (8.0). Biometrics alone are not sufficient, as they can be compromised (e.g., copies of fingerprints or facial recognition). The combination of multiple factors strengthens security and reduces the risk of unauthorized access. This practice aligns with best security practices and GDPR requirements to protect personal data. | J51: Multi-factor authentication frameworks that support biometrics as a secondary factor (e.g., Auth0, Okta) Authentication management systems requiring multiple factors (e.g., Keycloak, Firebase Authentication) Regular audits to ensure compliance with multi-factor authentication policies ASP.NET Identity for integrating multi-factor authentication with biometrics as a secondary factor
A52: Cryptographic Verifier | B52: 2.9.1 | C52: 2 | D52: 320 | E52: 5.1.7.2 | F52: Verify that cryptographic keys used in verification are stored securely and protected against disclosure, such as using a Trusted Platform Module (TPM) or Hardware Security Module (HSM), or an OS service that can use this secure storage. | G52: Non-valid | I52: Ensuring that cryptographic keys used in verification are stored securely is essential to protect the AMAP against attacks such as "Unauthorized access to control functionalities" (7.2) and "Identity spoofing to gain unauthorized access" (8.0). The use of security modules, such as TPMs, HSMs, or secure storage services based on the operating system (e.g., Windows DPAPI, Android Keystore), protects the keys from extraction or disclosure, even in the event of partial system compromise. This practice aligns with best security practices and GDPR requirements to protect sensitive data. | J52: Trusted Platform Module (TPM) for secure key storage Hardware Security Modules (HSMs) (e.g., AWS CloudHSM, Azure Key Vault HSM) Secure storage services based on the operating system (e.g., Android Keystore, Apple Secure Enclave, Windows DPAPI) Authentication frameworks that support integration with secure storage (e.g., Auth0, Firebase Authentication) ASP.NET Identity for secure key storage and management in authentication systems
B53: 2.9.2 | C53: 2 | D53: 330 | E53: 5.1.7.2 | F53: Verify that the challenge nonce is at least 64 bits in length, and statistically unique or unique over the lifetime of the cryptographic device. | G53: Not Applicable | I53: Ensuring that the challenge nonce is at least 64 bits in length and statistically unique or unique during the lifetime of the cryptographic device is essential to protect the AMAP against replay attacks and spoofing. Unique nonces ensure that each cryptographic operation is distinct, preventing an attacker from reusing previous messages or responses. The use of cryptographically secure random number generators (CSPRNG) to create nonces is a recommended practice. This measure aligns with best security practices and helps protect sensitive data in compliance with the GDPR. | J53: Cryptographically Secure Random Number Generators (CSPRNG) (e.g., System.Security.Cryptography.RandomNumberGenerator in .NET) Cryptographic APIs that support the generation of unique nonces (e.g., OpenSSL, BouncyCastle) Authentication frameworks that use secure nonces (e.g., OAuth2, OpenID Connect) ASP.NET Identity for nonce generation in authentication processes Regular audits to verify the uniqueness and security of generated nonces
B54: 2.9.3 | C54: 2 | D54: 327 | E54: 5.1.7.2 | F54: Verify that approved cryptographic algorithms are used in the generation, seeding, and verification. | G54: Non-valid | I54: Ensuring the use of approved cryptographic algorithms for generation, initialization (seeding), and verification is essential to protect the AMAP from attacks such as "Credential interception during transmission" (7.8) and "Identity spoofing for unauthorized access" (8.0). Algorithms such as AES, RSA, HMAC-SHA256, HMAC-SHA512, and others approved by standards like NIST or recommended by OWASP guarantee the security and integrity of the data. The use of unapproved or obsolete algorithms can compromise the system's resistance to attacks. This practice aligns with security best practices and helps protect sensitive data in compliance with GDPR. | J54: Secure cryptographic libraries (e.g., OpenSSL, BouncyCastle, PyCryptodome) ASP.NET Core Identity: Provides authentication and data protection services, utilizing secure algorithms like HMAC-SHA256 for token signing and AES for data encryption, ensuring the use of approved cryptographic algorithms. Frameworks supporting approved cryptographic algorithms (e.g., Auth0, Firebase Authentication) Regular audits to verify compliance with approved cryptographic algorithms Security analysis tools to validate the implementation of cryptographic algorithms
A55: Service Authentication | B55: 2.10.1 | C55: LVL2: OS assisted, LVL3: HSM | D55: 287 | E55: 5.1.1.1 | F55: Verify that intra-service secrets do not rely on unchanging credentials such as passwords, API keys or shared accounts with privileged access. | G55: Non-valid | I55: Avoiding the use of static and unchangeable credentials, such as passwords, API keys, or shared accounts with privileged access, is crucial to protect the AMAP from threats like "Unauthorized access to control functionalities" (7.2) and "Identity spoofing for unauthorized access" (8.0). Static credentials are vulnerable to brute-force attacks, reuse, and compromise. Instead, it is recommended to use dynamic mechanisms, such as short-lived tokens (OAuth2), certificate-based authentication, or automatic credential rotation systems. This practice reduces the risk of compromise and is aligned with security best practices and GDPR requirements. | J55: Secret Management (e.g., HashiCorp Vault, AWS Secrets Manager, Azure Key Vault) Dynamic Access Tokens (e.g., OAuth2 with JWT) Automatic Credential Rotation through CI/CD tools (e.g., Jenkins, GitHub Actions) Authentication Frameworks that support short-lived tokens (e.g., Keycloak)
B56: 2.10.2 | C56: LVL2: OS assisted, LVL3: HSM | D56: 255 | E56: 5.1.1.1 | F56: Verify that if passwords are required for service authentication, the service account used is not a default credential. (e.g. root/root or admin/admin are default in some services during installation). | G56: Valid | I56: The use of default credentials for service accounts poses a significant risk to the AMAP, especially considering threats like "Identity spoofing for unauthorized access" (8.0) and "Unauthorized access to control functionalities" (7.2). Default credentials are widely known and often exploited by attackers to compromise systems. Ensuring that these credentials are changed during the initial configuration of the service is essential to mitigate this risk. This practice is aligned with security best practices and GDPR requirements to protect sensitive data. | J56: Automated configuration scripts to enforce the change of default credentials during installation. Security auditing tools to detect default credentials (e.g., Nessus, OpenVAS). Service account management with unique and secure credentials (e.g., HashiCorp Vault, AWS Secrets Manager).
B57: 2.10.3 | C57: LVL2: OS assisted, LVL3: HSM | D57: 522 | E57: 5.1.1.1 | F57: Verify that passwords are stored with sufficient protection to prevent offline recovery attacks, including local system access. | G57: Valid | H57: Program.cs — PasswordHasherOptions: IdentityV3, IterationCount=100000 (linha com builder.Services.Configure<PasswordHasherOptions>). | I57: Storing passwords with sufficient protection to prevent offline attacks, such as brute force or dictionary attacks, is essential for the AMAP, considering threats like "Interception of credentials during transmission" (7.8) and "Access to sensitive user information" (7.8). Passwords should be stored using secure hashing algorithms such as bcrypt, Argon2, or PBKDF2, with salting and an appropriate cost factor. This ensures that even in the case of local system access, passwords cannot be easily retrieved. This practice aligns with best security practices and GDPR requirements for protecting personal data. | J57: Secure hashing libraries (e.g., bcrypt, Argon2, PBKDF2). Authentication frameworks supporting secure hashing (e.g., ASP.NET Identity). Regular audits to verify compliance with secure password storage policies.
B58: 2.10.4 | C58: LVL2: OS assisted, LVL3: HSM | D58: 798 | F58: Verify passwords, integrations with databases and third-party systems, seeds and internal secrets, and API keys are managed securely and not included in the source code or stored within source code repositories. Such storage SHOULD resist offline attacks. The use of a secure software key store (L1), hardware TPM, or an HSM (L3) is recommended for password storage. | G58: Non-valid | I58: Managing passwords, API keys, seeds, and internal secrets securely is crucial to protect the AMAP from threats such as "Unauthorized access to control features" (7.2) and "Identity spoofing for unauthorized access" (8.0). Storing these secrets in the source code or repositories exposes the system to offline attacks, especially if the repository is compromised. Using tools such as secret managers (e.g., HashiCorp Vault, AWS Secrets Manager) or secure hardware devices (e.g., HSMs, TPMs) ensures that secrets are protected from unauthorized access. This practice aligns with best security practices and GDPR requirements to protect sensitive data. | J58: Secret managers (e.g., HashiCorp Vault, AWS Secrets Manager, Azure Key Vault). Hardware Security Modules (HSMs) (e.g., AWS CloudHSM, Azure Key Vault HSM). Secure software key stores (e.g., Docker Secrets, Kubernetes Secrets). Code analysis tools to detect secrets in repositories (e.g., GitGuardian, TruffleHog).

Sheet Session Management
A1: Area | B1: # | C1: ASVS Level | D1: CWE | E1: NIST | F1: Verification Requirement | G1: Valid | H1: Source Code Reference | I1: Comment | J1: Tool Used
A2: Fundamental Session Management Security | B2: 3.1.1 | C2: 1 | D2: 598 | F2: Verify the application never reveals session tokens in URL parameters or error messages. | G2: Valid | H2: //Program.cs options.Cookie.HttpOnly = true; options.Cookie.SecurePolicy = CookieSecurePolicy.Always; context.Response.StatusCode = 401; | I2: A aplicação não envia tokens na URL (usa cookies HTTP-only para a sessão) e não expõe tokens em mensagens de erro (responde com 401 sem redirecionar nem revelar detalhes). | J2: ASP.NET Core + Identity
A3: Session Binding | B3: 3.2.1 | C3: 1 | D3: 384 | E3: 7.1 | F3: Verify the application generates a new session token on user authentication. ([C6](https://www.owasp.org/index.php/OWASP_Proactive_Controls#tab=Formal_Numbering)) | G3: Valid | H3: //Program.cs Gerido automaticamente por: .AddDefaultTokenProviders() e pelo middleware UseAuthentication() | I3: O ASP.NET Core gera automaticamente um novo cookie/token seguro após login. Nenhum cookie de sessão é reutilizado entre sessões. | J3: ASP.NET Core Identity
B4: 3.2.2 | C4: 1 | D4: 331 | E4: 7.1 | F4: Verify that session tokens possess at least 64 bits of entropy. ([C6](https://www.owasp.org/index.php/OWASP_Proactive_Controls#tab=Formal_Numbering)) | G4: Valid | H4: //Program.cs Gerado internamente por DataProtectionTokenProvider<TUser> e cookies seguros (.AddDefaultTokenProviders()) | I4: Os cookies de autenticação usam tokens com entropia adequada (>= 64 bits), conforme a especificação do .NET. Não é necessário gerar manualmente. | J4: ASP.NET Core Identity
B5: 3.2.3 | C5: 1 | D5: 539 | E5: 7.1 | F5: Verify the application only stores session tokens in the browser using secure methods such as appropriately secured cookies (see section 3.4) or HTML 5 session storage. | G5: Valid | H5: //Program.cs options.Cookie.HttpOnly = true; options.Cookie.SecurePolicy = CookieSecurePolicy.Always; options.Cookie.SameSite = SameSiteMode.Strict; | I5: A sessão é armazenada com cookies HttpOnly e Secure, o que evita acesso via JavaScript e exige HTTPS. | J5: ASP.NET Core
B6: 3.2.4 | C6: 2 | D6: 331 | E6: 7.1 | F6: Verify that session tokens are generated using approved cryptographic algorithms. ([C6](https://www.owasp.org/index.php/OWASP_Proactive_Controls#tab=Formal_Numbering)) | G6: Valid | H6: //Program.cs Implementado por default com o sistema de DataProtection do ASP.NET Core e AddDefaultTokenProviders() | I6: O ASP.NET utiliza algoritmos seguros (ex: AES-256 + HMACSHA256) para gerar e proteger tokens. Não há necessidade de implementação manual. | J6: ASP.NET Core + Data Protection API
A7: Session Termination | B7: 3.3.1 | C7: 1 | D7: 613 | E7: 7.1 | F7: Verify that logout and expiration invalidate the session token, such that the back button or a downstream relying party does not resume an authenticated session, including across relying parties. ([C6](https://owasp.org/www-project-proactive-controls/#div-numbering)) | G7: Valid | H7: //Program.cs await _signInManager.SignOutAsync(); e options.ExpireTimeSpan, SlidingExpiration | I7: O método SignOutAsync() limpa o cookie de autenticação e a sessão expira corretamente. Após logout, não é possível retomar sessão com o botão voltar. | J7: ASP.NET Core Identity
B8: 3.3.2 | C8: 1 | D8: 613 | E8: 7.2 | F8: If authenticators permit users to remain logged in, verify that re-authentication occurs periodically both when actively used or after an idle period. ([C6](https://owasp.org/www-project-proactive-controls/#div-numbering)) * L1: 30 days * L2: 12 hours or 30 minutes of inactivity, 2FA optional * L3: 12 hours or 15 minutes of inactivity, with 2FA | G8: Valid | H8: //Program.cs options.ExpireTimeSpan = TimeSpan.FromMinutes(30); SlidingExpiration = true/false | I8: O tempo de sessão pode ser ajustado para cumprir os níveis L1–L3. A reautenticação pode ser forçada após X minutos de inatividade. | J8: ASP.NET Core Identity
B9: 3.3.3 | C9: 2 | D9: 613 | F9: Verify that the application gives the option to terminate all other active sessions after a successful password change (including change via password reset/recovery), and that this is effective across the application, federated login (if present), and any relying parties. | G9: Non-valid | H9: Password Change Implementation is on AccountController.cs | I9: No implementation found for password change functionality and no mechanism to terminate other active sessions. | J9: ASP.NET Core Identity, Microsoft.AspNetCore.Authentication, Microsoft.AspNetCore.Session and Microsoft.AspNetCore.Identity.EntityFrameworkCore for Backend, Session middleware, Identity framework and Microsoft.AspNetCore.Authentication.JwtBearer
B10: 3.3.4 | C10: 2 | D10: 613 | E10: 7.1 | F10: Verify that users are able to view and (having re-entered login credentials) log out of any or all currently active sessions and devices. | G10: Non-valid | H10: Logout Implementation is on AccountController.cs, Session Configuration on Program.cs. | I10: No implementation for viewing active sessions and no mechanism to log out from specific sessions. No functionality to log out from all sessions except current and no device tracking mechanism. No re-authentication requirements for session management and only basic logout functionality for current session exists. | J10: ASP.NET Core Identity, Database Storage for Sessions, Session Management
A11: Cookie-based Session Management | B11: 3.4.1 | C11: 1 | D11: 614 | E11: 7.1.1 | F11: Verify that cookie-based session tokens have the 'Secure' attribute set. ([C6](https://owasp.org/www-project-proactive-controls/#div-numbering)) | G11: Valid | H11: //Program.cs options.Cookie.SecurePolicy = CookieSecurePolicy.Always; | I11: O atributo Secure é corretamente definido, impedindo envio do cookie por HTTP. | J11: ASP.NET Core Identity
B12: 3.4.2 | C12: 1 | D12: 1004 | E12: 7.1.1 | F12: Verify that cookie-based session tokens have the 'HttpOnly' attribute set. ([C6](https://owasp.org/www-project-proactive-controls/#div-numbering)) | G12: Valid | H12: //Program.cs options.Cookie.HttpOnly = true; | I12: O cookie é marcado como HttpOnly, prevenindo roubo via XSS. | J12: ASP.NET Core Identity
B13: 3.4.3 | C13: 1 | D13: 16 | E13: 7.1.1 | F13: Verify that cookie-based session tokens utilize the 'SameSite' attribute to limit exposure to cross-site request forgery attacks. ([C6](https://owasp.org/www-project-proactive-controls/#div-numbering)) | G13: Valid | H13: //Program.cs options.Cookie.SameSite = SameSiteMode.Strict; | I13: SameSite pode ser configurado conforme o risco e necessidade (ex: Strict ou Lax). | J13: ASP.NET Core Identity
B14: 3.4.4 | C14: 1 | D14: 16 | E14: 7.1.1 | F14: Verify that cookie-based session tokens use the "__Host-" prefix so cookies are only sent to the host that initially set the cookie. | G14: Non-valid | H14: Program.cs contains session and authentication cookie configurations in AddSession(...), and Authentication cookie configuration in ConfigureApplicationCookie(...) | I14: The application does not implement the "Host-" prefix for cookie names. There is no configuration setting the cookie name with this prefix in either the session or authentication cookie setup. The "_Host-" prefix is a security feature that, when combined with secure and path=/ attributes, ensures cookies are only sent to the host that initially set them, preventing cross-subdomain cookie leakage. This additional security measure is missing from the current implementation. | J14: ASP.NET Core Identity, Microsoft.AspNetCore.Authentication, Microsoft.AspNetCore.Session, Cookie authentication middleware, ASP.NET Core Cookie configuration
B15: 3.4.5 | C15: 1 | D15: 16 | E15: 7.1.1 | F15: Verify that if the application is published under a domain name with other applications that set or use session cookies that might disclose the session cookies, set the path attribute in cookie-based session tokens using the most precise path possible. ([C6](https://owasp.org/www-project-proactive-controls/#div-numbering)) | G15: Non-valid | H15: Program.cs contains session configuration with SameSite attribute in AddSession(...) and for authentication cookies there is ConfigureApplicationCookie(...) | I15: The application does not explicitly set the Path attribute for cookies to the most precise path possible. There is no configuration in either the session or authentication cookie setup that restricts the cookies to specific application paths. By default, cookies in ASP.NET Core are set with the path "/", making them available across all paths of the domain. | J15: ASP.NET Core Identity, Microsoft.AspNetCore.Authentication, Microsoft.AspNetCore.Session, Cookie authentication middleware, ASP.NET Core Cookie configuration
A16: Token-based Session Management | B16: 3.5.1 | C16: 2 | D16: 290 | E16: 7.1.2 | F16: Verify the application allows users to revoke OAuth tokens that form trust relationships with linked applications. | G16: Not Applicable | H16: There is not any implementation related to OAuth token management or revocation in the codebase. | I16: The application does not implement Outh authentication or authorization. There is no functionality for users to manage or revoke OAuth tokens for linked applications. The authentication system is based on ASP.NET Core Identity with cookie-based authentication rather than OAuth token-based authentication. No OAuth token storage, management, or revocation mechanisms were found in the codebase. No controllers or endpoints exist for users to view or manage external application connections. | J16: ASP.NET Core Identity, Microsoft.AspNetCore.Authentication, Cookie authentication middleware, ASP.NET Core Authentication configuration
B17: 3.5.2 | C17: 2 | D17: 798 | F17: Verify the application uses session tokens rather than static API secrets and keys, except with legacy implementations. | G17: Valid | H17: //Program.cs builder.Services.AddIdentity<AppUser, IdentityRole>(...) .AddEntityFrameworkStores<AppDbContext>() .AddDefaultTokenProviders(); | I17: Usa AddDefaultTokenProviders para gerar tokens temporários e seguros, evitando segredos estáticos. | J17: ASP.NET Core Identity
B18: 3.5.3 | C18: 2 | D18: 345 | F18: Verify that stateless session tokens use digital signatures, encryption, and other countermeasures to protect against tampering, enveloping, replay, null cipher, and key substitution attacks. | G18: Valid | H18: //Program.cs builder.Services.ConfigureApplicationCookie(options => { options.Cookie.HttpOnly = true; options.Cookie.SecurePolicy = CookieSecurePolicy.Always; options.SlidingExpiration = true; ... }); | I18: Tokens de sessão e cookies são protegidos via configurações do Identity e HTTPS. | J18: ASP.NET Core Identity + Cookies
A19: Federated Re-authentication | B19: 3.6.1 | C19: 3 | D19: 613 | E19: 7.2.1 | F19: Verify that Relying Parties (RPs) specify the maximum authentication time to Credential Service Providers (CSPs) and that CSPs re-authenticate the subscriber if they haven't used a session within that period. | G19: Not Applicable | H19: Program.cs contains session timeout configuration but no RP-CSP specification, and no implementation of external authentication providers or federation found in the controller, like AccountController.cs | I19: The application does not implement a federated authentication system with Relying Parties (RPs) and Credential Service Providers (CSPs). There is no code that specifies maximum authentication time to external identity providers, nor mechanisms to enforce re-authentication based on such specifications. | J19: ASP.NET Core Identity, Microsoft.AspNetCore.Authentication, Microsoft.AspNetCore.Session, Cookie authentication middleware, ASP.NET Core Session configuration.
B20: 3.6.2 | C20: 3 | D20: 613 | E20: 7.2.1 | F20: Verify that Credential Service Providers (CSPs) inform Relying Parties (RPs) of the last authentication event, to allow RPs to determine if they need to re-authenticate the user. | G20: Not Applicable | H20: Non-valid | I20: The application does not function as a Credential Service rovider (CSP) and does not implement any mechanism to inform Relying Parties (RPs) about authentication events. The authentication system is a standalone implementation using ASP.NET Core Identity with no federation capabilities. | J20: ASP.NET Core Identity, Microsoft.AspNetCore.Authentication, Microsoft.AspNetCore.Session, Cookie authentication middleware, ASP.NET Core Identity configuration
A21: Defenses Against Session Management Exploits | B21: 3.7.1 | C21: 1 | D21: 778 | F21: Verify the application ensures a valid login session or requires re-authentication or secondary verification before allowing any sensitive transactions or account modifications. | G21: Valid | H21: //Program.cs app.UseAuthentication(); app.UseAuthorization(); | I21: A aplicação protege endpoints com autenticação (UseAuthentication) e autorização (UseAuthorization), o que impede acessos não autenticados. No entanto, não implementa reautenticação ou verificação explícita da validade da sessão antes de ações críticas como alteração de dados de conta. | J21: ASP.NET Core Identity

Sheet Access Control
A1: Area | B1: # | C1: ASVS Level | D1: CWE | E1: NIST | F1: Verification Requirement | G1: Valid | H1: Source Code Reference | I1: Comment | J1: Tool Used
A2: General Access Control Design | B2: 4.1.1 | C2: 1 | D2: 602 | F2: Verify that the application enforces access control rules on a trusted service layer, especially if client-side access control is present and could be bypassed. | G2: Valid | H2: Program.cs (lines 63-68): // Configuração das roles de autorização builder.Services.AddAuthorization(options => { options.AddPolicy("Manager", policy => policy.RequireRole("Manager")); options.AddPolicy("Producer", policy => policy.RequireRole("Producer")); options.AddPolicy("CoProducer", policy => policy.RequireRole("CoProducer")); }); PaymentController.cs (line 11): [Authorize(Roles = nameof(UserType.CoProducer))] DeliveryBc.cs (lines 29-33): // Verificar se o produtor atual tem permissão if (subscription.ProductOffer == null || subscription.ProductOffer.Product.ProducerId != currentProducerId) throw new UnauthorizedAccessException("You are not allowed to update this subscription."); | I2: Requisito aplicado com controlo de acesso central no backend: uso de [Authorize] no controller e validação adicional na camada de business. | J2: ASP.NET Core Identity
B3: 4.1.2 | C3: 1 | D3: 639 | F3: Verify that all user and data attributes and policy information used by access controls cannot be manipulated by end users unless specifically authorized. | G3: Valid | H3: using Microsoft.AspNetCore.Mvc; using System.Security.Claims; namespace AMAP.Api.Controllers { public class BaseController : Controller { protected string GetLoggedId() => User.Claims.FirstOrDefault(c => c.Type.Equals(ClaimTypes.NameIdentifier))?.Value; } } | I3: Obtém ID do utilizador autenticado via claims do token — evita manipulação pelo cliente. | J3: ASP.NET Core Identity / JWT Middleware (System.Security.Claims)
B4: 4.1.3 | C4: 1 | D4: 285 | F4: Verify that the principle of least privilege exists - users should only be able to access functions, data files, URLs, controllers, services, and other resources, for which they possess specific authorization. This implies protection against spoofing and elevation of privilege. ([C7](https://owasp.org/www-project-proactive-controls/#div-numbering)) | G4: Valid | H4: [Authorize(Roles = nameof(UserType.Manager))] [HttpPost()] public async Task<IActionResult> CreateSubscriptionPeriodAndDeliveryDate([FromBody] SubscriptionPeriod subscriptionPeriod) { try { var created = await _subscriptionPeriodBc.CreateSubscriptionPeriodAndDeliveryDateAsync(subscriptionPeriod); return CreatedAtAction(nameof(GetSubscriptionPeriodById), new { id = created.Id }, created); } catch (ArgumentException ex) { return BadRequest(new { message = ex.Message }); } catch (InvalidOperationException ex) { return BadRequest(new { message = ex.Message }); } } | I4: Acesso restrito a utilizadores com o papel "Manager" — segue o princípio do menor privilégio. | J4: ASP.NET Core Identity
B5: 4.1.4 | C5: 1 | D5: 276 | F5: [DELETED, DUPLICATE OF 4.1.3] | G5: Not Applicable
B6: 4.1.5 | C6: 1 | D6: 285 | F6: Verify that access controls fail securely including when an exception occurs. ([C10](https://owasp.org/www-project-proactive-controls/#div-numbering)) | G6: Valid | H6: //ProductController.cs [HttpGet("export-to-file")] public IActionResult ExportProductsToFile() { var producerId = User.Claims.FirstOrDefault(c => c.Type == ClaimTypes.NameIdentifier)?.Value; if (string.IsNullOrEmpty(producerId)) { return Unauthorized(new { message = "Producer not authenticated" }); } | I6: Falha de autenticação devolve 401 — controlo de acesso falha de forma segura. | J6: ASP.NET Core Authorization
A7: Operation Level Access Control | B7: 4.2.1 | C7: 1 | D7: 639 | F7: Verify that sensitive data and APIs are protected against Insecure Direct Object Reference (IDOR) attacks targeting creation, reading, updating and deletion of records, such as creating or updating someone else's record, viewing everyone's records, or deleting all records. | G7: Valid | H7: //ProductController.cs [HttpDelete("{id}")] public IActionResult DeleteProduct(int id) { var producerId = User.Claims.FirstOrDefault(c => c.Type.Equals(ClaimTypes.NameIdentifier))?.Value; try { _productBc.DeleteProduct(id, producerId); return NoContent(); } catch (ArgumentException ex) { return BadRequest(new { message = ex.Message }); } catch (KeyNotFoundException ex) { return NotFound(new { message = ex.Message }); } } | I7: Protege a operação de DELETE com verificação do utilizador autenticado — previne IDOR. | J7: ASP.NET Core Claims-based Authorization (via System.Security.Claims)
B8: 4.2.2 | C8: 1 | D8: 352 | F8: Verify that the application or framework enforces a strong anti-CSRF mechanism to protect authenticated functionality, and effective anti-automation or anti-CSRF protects unauthenticated functionality. | G8: Valid | H8: //Program.cs // Configuração do Identity e cookie de autenticação builder.Services.AddIdentity<AppUser, IdentityRole>() .AddEntityFrameworkStores<AppDbContext>() .AddDefaultTokenProviders(); // Configuração do cookie de autenticação para login/logout e segurança básica builder.Services.ConfigureApplicationCookie(options => { options.LoginPath = "/api/account/login"; options.LogoutPath = "/api/account/logout"; options.SlidingExpiration = true; // Configurações de cookie (secure, SameSite) dependendo do ambiente }); // Uso dos middlewares app.UseAuthentication(); app.UseAuthorization(); | I8: A aplicação implementa proteção anti-CSRF parcial, mas com limitações importantes. Em produção, a proteção baseia-se principalmente no atributo SameSite dos cookies, que oferece uma proteção básica, mas não é uma solução completa contra CSRF. | J8: ASP.NET Core CORS middleware, Cookie configuration, SameSite cookie attributes, HTTPS enforcement (in production).
A9: Other Access Control Considerations | B9: 4.3.1 | C9: 1 | D9: 419 | F9: Verify administrative interfaces use appropriate multi-factor authentication to prevent unauthorized use. | G9: Valid | H9: AMAP/AMAP_API/Controllers/TwoFactorAuthController.cs (Enforces MFA for "Manager" role). | I9: MFA is implemented and enforced for users with the "Manager" role, who represent the administrative users of the application. | J9: ASP.NET Core Identity, Google.Authenticator library
B10: 4.3.2 | C10: 1 | D10: 548 | F10: Verify that directory browsing is disabled unless deliberately desired. Additionally, applications should not allow discovery or disclosure of file or directory metadata, such as Thumbs.db, .DS_Store, .git or .svn folders. | G10: Valid | H10: No Program.cs a aplicação não utiliza UseDirectoryBrowser(), logo a navegação de diretórios está desativada por defeito. | I10: A funcionalidade de listagem de diretórios (UseDirectoryBrowser) não está ativada no Program.cs | J10: Análise manual do Program.cs
B11: 4.3.3 | C11: 2 | D11: 732 | F11: Verify the application has additional authorization (such as step up or adaptive authentication) for lower value systems, and / or segregation of duties for high value applications to enforce anti-fraud controls as per the risk of application and past fraud. | G11: Non-valid | H11: //Progam.cs // Configuração das roles de autorização – apenas roles, sem step-up ou MFA adicional builder.Services.AddAuthorization(options => { options.AddPolicy("Manager", policy => policy.RequireRole("Manager")); options.AddPolicy("Producer", policy => policy.RequireRole("Producer")); options.AddPolicy("CoProducer",policy => policy.RequireRole("CoProducer")); }); | I11: Falta qualquer “step-up” ou autorização adaptativa para operações sensíveis e não há segregação de funções para operações de alto risco. | J11: Análise manual do Program.cs e do AccountController.cs

Sheet Validation, Sanitization and En
A1: Area | B1: # | C1: ASVS Level | D1: CWE | E1: NIST | F1: Verification Requirement | G1: Valid | H1: Source Code Reference | I1: Comment | J1: Tool Used
A2: Input Validation | B2: 5.1.1 | C2: 1 | D2: 235 | F2: Verify that the application has defenses against HTTP parameter pollution attacks, particularly if the application framework makes no distinction about the source of request parameters (GET, POST, cookies, headers, or environment variables). | G2: Valid | H2: AMAP/AMAP_API/Program.cs (Standard ASP.NET Core configuration). AMAP/AMAP_API/Controllers/AccountController.cs (Example: [FromHeader(Name = "User-Agent")] in Login and LogOff methods, use of [FromBody] in Login method). | I2: ASP.NET Core's model binding inherently defends against parameter pollution by strictly mapping parameters to expected types and sources. Explicit use of [FromHeader] and [FromBody] attributes further strengthens these defenses. | J2: ASP.NET Core Model Binding, [FromHeader] attribute, [FromBody] attribute, ModelState.IsValid
B3: 5.1.2 | C3: 1 | D3: 915 | F3: Verify that frameworks protect against mass parameter assignment attacks, or that the application has countermeasures to protect against unsafe parameter assignment, such as marking fields private or similar. ([C5](https://owasp.org/www-project-proactive-controls/#div-numbering)) | G3: Valid | H3: AMAP/AMAP_API/Controllers/AccountController.cs (Uses LoginViewModel, RegisterViewModel, ChangePasswordViewModel, ResetPasswordViewModel for input parameters). | I3: The application uses ViewModels/DTOs for input parameters, which is the recommended practice in ASP.NET Core to prevent mass assignment by only binding intended properties. | J3: ASP.NET Core Model Binding, Use of ViewModels/DTOs
B4: 5.1.3 | C4: 1 | D4: 20 | F4: Verify that all input (HTML form fields, REST requests, URL parameters, HTTP headers, cookies, batch files, RSS feeds, etc) is validated using positive validation (allow lists). ([C5](https://owasp.org/www-project-proactive-controls/#div-numbering)) | G4: Non-valid | H4: AccountController.cs shows basic validation but no clear allowlisting in Login(...). | I4: The application lacks evidence of comprehensive positive validation (allowlisting) accross all input types. | J4: ASP.NET Core model validation, ModelState validation in controllers, Data annotations (inferred).
B5: 5.1.4 | C5: 1 | D5: 20 | F5: Verify that structured data is strongly typed and validated against a defined schema including allowed characters, length and pattern (e.g. credit card numbers, e-mail addresses, telephone numbers, or validating that two related fields are reasonable, such as checking that suburb and zip/postcode match). ([C5](https://owasp.org/www-project-proactive-controls/#div-numbering)) | G5: Non-valid | H5: AccountController.cs shows basic validation in Login(...). | I5: The application shows insifficient evidence of strong typing and schema validation. Without seeing the complete model definitions with their validation attributes, it's impossible to confirm that proper schema validation is implemented. The visible code only shows basic validation checks without the detailed constraints that would be necessary for proper structured data validation. | J5: ASP.NET Core model validation, ModelState validation in controllers, Strong typing in C# classes.
B6: 5.1.5 | C6: 1 | D6: 601 | F6: Verify that URL redirects and forwards only allow destinations which appear on an allow list, or show a warning when redirecting to potentially untrusted content. | G6: Non-valid | H6: Found limited evidence of redirects in the frontend code in LoginSignUp.js. | I6: Based on the limited code available, the application does not show comprehensive protection against open redirect vulnerabilities. | J6: We are using Frontend navigation (window.location.href), React routing (inferred), No visible server-side redirect validation tools or mechanisms
A7: Sanitization and Sandboxing | B7: 5.2.1 | C7: 1 | D7: 116 | F7: Verify that all untrusted HTML input from WYSIWYG editors or similar is properly sanitized with an HTML sanitizer library or framework feature. ([C5](https://owasp.org/www-project-proactive-controls/#div-numbering)) | G7: Non-valid | H7: No clear evidence of WYSIWYG editors or HTML input handling was found. | I7: Based on the limited code available, there is no evidence that the application handles untrusted HTML input or implements proper HTML sanitization.
B8: 5.2.2 | C8: 1 | D8: 138 | F8: Verify that unstructured data is sanitized to enforce safety measures such as allowed characters and length. | G8: Non-valid | H8: Limited evidence of input handling without explicit sanitization. | I8: The application shows insifficient evidence of sanitizing unstructed data. | J8: No dedicated sanitization tools visible.
B9: 5.2.3 | C9: 1 | D9: 147 | F9: Verify that the application sanitizes user input before passing to mail systems to protect against SMTP or IMAP injection. | G9: Non-valid | H9: Found partial email handling in Program.cs in AddSingleton<>() | I9: Baseed on the limit evidence, the application does not show proper sanitization for email-related inputs. | J9: No visible email sanitization tools or libraries.
B10: 5.2.4 | C10: 1 | D10: 95 | F10: Verify that the application avoids the use of eval() or other dynamic code execution features. Where there is no alternative, any user input being included must be sanitized or sandboxed before being executed. | G10: Valid | H10: No instances of dynamic code execution were found in the server-side C# code examined, including in Login(...). | I10: The application correctly avoids dynamic code xecution features.
B11: 5.2.5 | C11: 1 | D11: 94 | F11: Verify that the application protects against template injection attacks by ensuring that any user input being included is sanitized or sandboxed. | G11: Valid | H11: AMAP/AMAP_API/Controllers/*.cs (Use of strongly-typed ViewModels/DTOs, ASP.NET Core model binding, and System.Text.Json serialization). amap-ui/src/*.js (React frontend using JSX, which auto-escapes content). | I11: The application is a REST API (ASP.NET Core) without server-side templating (e.g., Razor). It uses strong model binding, DTOs, and JSON serialization (which escapes special characters). The React frontend (using JSX) also auto-escapes content. | J11: ASP.NET Core Model Binding, System.Text.Json, React (JSX)
B12: 5.2.6 | C12: 1 | D12: 918 | F12: Verify that the application protects against SSRF attacks, by validating or sanitizing untrusted data or HTTP file metadata, such as filenames and URL input fields, and uses allow lists of protocols, domains, paths and ports. | G12: Non-valid | H12: Limited evidence of URL or file handling in the code. | I12: Based on the available code, SSRF protection measures are not evident.
B13: 5.2.7 | C13: 1 | D13: 159 | F13: Verify that the application sanitizes, disables, or sandboxes user-supplied Scalable Vector Graphics (SVG) scriptable content, especially as they relate to XSS resulting from inline scripts, and foreignObject. | G13: Non-valid | H13: No evidence of SVG handling was found in the code. | I13: Based on the code, SVG content handling annot be properly assessed.
B14: 5.2.8 | C14: 1 | D14: 94 | F14: Verify that the application sanitizes, disables, or sandboxes user-supplied scriptable or expression template language content, such as Markdown, CSS or XSL stylesheets, BBCode, or similar. | G14: Non-valid | H14: No evidence of handling scriptable content like Markdown or CSS was found in the code. | I14: Based on the code, handling of scriptable content formats cannot be assessed.
A15: Output encoding and Injection Prevention | B15: 5.3.1 | C15: 1 | D15: 116 | F15: Verify that output encoding is relevant for the interpreter and context required. For example, use encoders specifically for HTML values, HTML attributes, JavaScript, URL parameters, HTTP headers, SMTP, and others as the context requires, especially from untrusted inputs (e.g. names with Unicode or apostrophes, such as ねこ or O'Hara). ([C4](https://owasp.org/www-project-proactive-controls/#div-numbering)) | G15: Valid | H15: ASP.NET Core's default JSON serialization. React's JSX auto-escaping. | I15: The backend uses JSON serialization which automatically escapes special characters. The React frontend's JSX auto-escapes content rendered into HTML, preventing XSS. | J15: ASP.NET Core JSON Serialization, React (JSX)
B16: 5.3.2 | C16: 1 | D16: 176 | F16: Verify that output encoding preserves the user's chosen character set and locale, such that any Unicode character point is valid and safely handled. ([C4](https://owasp.org/www-project-proactive-controls/#div-numbering)) | G16: Valid | H16: ASP.NET Core's default UTF-8 encoding for HTTP responses. React's Unicode-aware rendering. | I16: The backend serves UTF-8 encoded JSON responses, and the frontend (React) correctly handles and displays Unicode characters, ensuring character set and locale preservation. | J16: ASP.NET Core (UTF-8 encoding), React (Unicode support)
B17: 5.3.3 | C17: 1 | D17: 79 | F17: Verify that context-aware, preferably automated - or at worst, manual - output escaping protects against reflected, stored, and DOM based XSS. ([C4](https://owasp.org/www-project-proactive-controls/#div-numbering)) | G17: Valid | H17: ASP.NET Core's default JSON serialization. React's JSX auto-escaping. | I17: Both backend (JSON serialization) and frontend (React JSX) use automated, context-aware output escaping to prevent reflected, stored, and DOM-based XSS attacks. | J17: ASP.NET Core JSON Serialization, React (JSX)
B18: 5.3.4 | C18: 1 | D18: 89 | F18: Verify that data selection or database queries (e.g. SQL, HQL, ORM, NoSQL) use parameterized queries, ORMs, entity frameworks, or are otherwise protected from database injection attacks. ([C3](https://owasp.org/www-project-proactive-controls/#div-numbering)) | G18: Valid | H18: In Program.cs shows Entity Framework Core configuration in AddDbContext<...>(...) and in AddScoped<...>(). AccountController.cs uses Entity Framework with parametrized methods in FindByEmailAsync(...) and in GetRolesAsync(...). And in Repository pattern implementation is referenced in Program.cs, suggesting proper data access abstraction in AddScoped<...>(). | I18: The application properly protects against database injection. | J18: Entity Framework Core, Repository patterns (IUnitOfWork), ASP.NET Core Identity, LINQ, Parametrized queries through ORMs.
B19: 5.3.5 | C19: 1 | D19: 89 | F19: Verify that where parameterized or safer mechanisms are not present, context-specific output encoding is used to protect against injection attacks, such as the use of SQL escaping to protect against SQL injection. ([C3, C4](https://owasp.org/www-project-proactive-controls/#div-numbering)) | G19: Valid | H19: Program.cs shows exclusive use of Entity Framework Core in AddDbContext<...>(...) and in AddScoped<...>(). | I19: The application meets this requirement through proper architecture. | J19: Entity Framework Core, Repository patterns (IUnitOfWork), ASP.NET Core Identity, LINQ, Parametrized queries through ORMs.
B20: 5.3.6 | C20: 1 | D20: 830 | F20: Verify that the application protects against JSON injection attacks, JSON eval attacks, and JavaScript expression evaluation. ([C4](https://owasp.org/www-project-proactive-controls/#div-numbering)) | G20: Non-valid | H20: No specific JSON validation, sanitization, or protection mechanisms were found in the code. | I20: Base on the code, protection against JSON-related attacks is not evident.
B21: 5.3.7 | C21: 1 | D21: 943 | F21: Verify that the application protects against LDAP injection vulnerabilities, or that specific security controls to prevent LDAP injection have been implemented. ([C4](https://owasp.org/www-project-proactive-controls/#div-numbering)) | G21: Valid | H21: Program.cs shows standard Identity configuration in AddIdentity and AccountController.cs uses Identity for authentication in PasswordSignInAsync(...). | I21: This requirement is valid because the application does not use LDAP for authentication or directory services, Authentication is handled through ASP.NET Core Identity with Entity Framework storage, No LDAP queries or connections were found in the codebase, No LDAP-related libraries or dependencies were identified and the application. | J21: ASP.NET Core Identity, Entity Framework Core for identity storage, No LDAP-related components identified.
B22: 5.3.8 | C22: 1 | D22: 78 | F22: Verify that the application protects against OS command injection and that operating system calls use parameterized OS queries or use contextual command line output encoding. ([C4](https://owasp.org/www-project-proactive-controls/#div-numbering)) | G22: Valid | H22: No evidence of OS command execution was found in the codebase. | I22: This requirement is considered valid because the application does not execute OS commands or system processes, No use of Process.Start(), System.Diagnostics.Process, or similar APIs, No shell command execution or command-line utilities invocation, No evidence of external program execution, | J22: No OS command execution components or utilities identified.
B23: 5.3.9 | C23: 1 | D23: 829 | F23: Verify that the application protects against Local File Inclusion (LFI) or Remote File Inclusion (RFI) attacks. | G23: Valid | H23: No evidence of file inclusion from user-controlled paths was found in the codebase. | I23: This requirement is considered valid because does not implement dynamic file inclusion based on user input, no evidence of including or loading files from user-controlled paths, no usage of file system operations with dynamic paths, no implementation of features that tipically lead to LFI/RFI (like themes, plugins, or custum includes) and standard fixed imports and references used throughout the codebase.
B24: 5.3.10 | C24: 1 | D24: 643 | F24: Verify that the application protects against XPath injection or XML injection attacks. ([C4](https://owasp.org/www-project-proactive-controls/#div-numbering)) | G24: Valid | H24: No evidence of XML processing or XPath queries was found in the codebase. | I24: This requirement is considered valid because the application does not use XML for data processing or storage, no XPath queries or XML parsing operation were found, the
A25: Memory, String and Unmanaged Code | B25: 5.4.1 | C25: 2 | D25: 120 | F25: Verify that the application uses memory-safe string, safer memory copy and pointer arithmetic to detect or prevent stack, buffer, or heap overflows. | G25: Valid | H25: The application is built with C# using ASP.NET Core, which inherently provides memory-safe operations, like Program.cs shows standard C# and ASP.NET Core usage in CreateBuilder(...) and AddController() in the builder created, and in AccountController | I25: This requirement is considered valid because C# is a memory-safe language with automatic garbage collection, ASP.NET Core provides memory-safe string handling and operations, the application does not use unsafe code blocks or direct memory manipulation, String operations use standard .NET memory-safe methods, no manual buffer management or pointer arithmetic was identified and the
B26: 5.4.2 | C26: 2 | D26: 134 | F26: Verify that format strings do not take potentially hostile input, and are constant. | G26: Valid | H26: No evidence of unsafe format string usage was found in the codebase. | I26: This requirement is consiered valid because the application uses constant string messages throughout the codebase, no evidence of using user input in format strings, error messages and notification use fixed strings, no string interpolation or formatting with user-controlled values, String concatenation operations (where visible) don't involve format specifiersand
B27: 5.4.3 | C27: 2 | D27: 190 | F27: Verify that sign, range, and input validation techniques are used to prevent integer overflows. | G27: Valid | H27: AMAP/AMAP.Models/ProductOffer.cs ([Range] on Price and Quantity). AMAP/AMAP.Models/Payment.cs ([Range] on AmountPaid). | I27: Numeric properties in data models now include [Range] attributes, ensuring values are within expected and safe numerical limits, preventing integer overflows from invalid input. | J27: ASP.NET Core Data Annotations ([Range])
A28: Deserialization Prevention | B28: 5.5.1 | C28: 1 | D28: 502 | F28: Verify that serialized objects use integrity checks or are encrypted to prevent hostile object creation or data tampering. ([C5](https://owasp.org/www-project-proactive-controls/#div-numbering)) | G28: Non-valid | H28: Limited evidence of object serialization was found in the provided code snippets. | I28: Based on the code, protection for serialized object is not evident.
B29: 5.5.2 | C29: 1 | D29: 611 | F29: Verify that the application correctly restricts XML parsers to only use the most restrictive configuration possible and to ensure that unsafe features such as resolving external entities are disabled to prevent XML eXternal Entity (XXE) attacks. | G29: Valid | H29: No evidence of XML parsing was found in the codebase. | I29: This requirement is considered valid because the application does not use XML parsing or processing, no XML-related libraries or parsers were found in the codebase, the
B30: 5.5.3 | C30: 1 | D30: 502 | F30: Verify that deserialization of untrusted data is avoided or is protected in both custom code and third-party libraries (such as JSON, XML and YAML parsers). | G30: Non-valid | H30: Limited evidence of deserialization operations in the provided code snippets. | I30: Based on the code available, deserialization protection is not evident.
B31: 5.5.4 | C31: 1 | D31: 95 | F31: Verify that when parsing JSON in browsers or JavaScript-based backends, JSON.parse is used to parse the JSON document. Do not use eval() to parse JSON. | G31: Valid | H31: Frontend Javascript | I31: This requirement is considered valid because the Frontend uses axios for API requests, which automatically parses JSON safely, no instances of eval() for JSON parsing were found in any JavaScript code, the Backend uses ASP.NET Core's built-in JSON deserialization which is safe,

Sheet Error Handling and Logging
A1: Area | B1: # | C1: ASVS Level | D1: CWE | E1: NIST | F1: Verification Requirement | G1: Valid | H1: Source Code Reference | I1: Comment | J1: Tool Used
A2: Log Content | B2: 7.1.1 | C2: 1 | D2: 532 | F2: Verify that the application does not log credentials or payment details. Session tokens should only be stored in logs in an irreversible, hashed form. ([C9, C10](https://owasp.org/www-project-proactive-controls/#div-numbering)) | G2: Valid | H2: // AccountController.cs lines 30-46 [HttpPost("login")] [AllowAnonymous] public async Task<IActionResult> Login([FromBody] LoginViewModel loginViewModel) { if (ModelState.IsValid) { var result = await _signInManager.PasswordSignInAsync(loginViewModel.Email, loginViewModel.Password, loginViewModel.RememberMe, lockoutOnFailure: true); // No direct logging of credentials } } | I2: The application doesn't explicitly log credentials or payment details in the code. Authentication is handled through ASP.NET Identity which doesn't log passwords by default. However, there's no structured logging strategy that defines what shouldn't be logged, and no explicit filtering or redaction of sensitive data in error scenarios. While not actively problematic, the application lacks safeguards against accidental logging of sensitive information | J2: Serilog or NLog with destructuring policies that redact sensitive information. Apply attributes or filters that prevent sensitive data from reaching logs. Use tools like grep or log analysis tools to scan logs for patterns indicating sensitive data leakage
B3: 7.1.2 | C3: 1 | D3: 532 | F3: Verify that the application does not log other sensitive data as defined under local privacy laws or relevant security policy. ([C9](https://owasp.org/www-project-proactive-controls/#div-numbering)) | G3: Non-valid | I3: The application doesn't have a comprehensive logging strategy with consideration for privacy laws. There are no log sanitization mechanisms, no data classification to identify what should be excluded from logs, and no explicit handling of personally identifiable information in logging contexts. This creates risk of accidentally logging sensitive data in violation of privacy regulations | J3: Logging policy with Serilog's Destructuring or NLog's Layout Renderers to exclude/mask PII. Use custom LoggerProvider implementations that filter sensitive data before writing to logs. Scan logs with tools like Microsoft's Data Classification Service or custom regex patterns to detect PII
B4: 7.1.3 | C4: 2 | D4: 778 | F4: Verify that the application logs security relevant events including successful and failed authentication events, access control failures, deserialization failures and input validation failures. ([C5, C7](https://owasp.org/www-project-proactive-controls/#div-numbering)) | G4: Valid | H4: // AccountController.cs lines 41-57 (no explicit logging of auth failures) if (result.IsLockedOut) { return StatusCode(423, new { message = "Account locked" }); } else { return Unauthorized(new { message = "Invalid login attempt" }); } | I4: The application doesn't systematically log security events. Authentication failures, access control decisions, input validation failures, and other security-relevant events are handled but not logged. The application's default logging configuration in appsettings.json exists, but there's no implementation of security event logging throughout the codebase | J4: Comprehensive security logging with Application Insights or Serilog/NLog with security-focused log sinks. Add logging middleware that captures security events automatically. Use OWASP Security Logging library or similar frameworks to standardize security event logging
B5: 7.1.4 | C5: 2 | D5: 778 | F5: Verify that each log event includes necessary information that would allow for a detailed investigation of the timeline when an event happens. ([C9](https://owasp.org/www-project-proactive-controls/#div-numbering)) | G5: Valid | H5: // appsettings.json lines 2-6 (basic logging config only) "Logging": { "LogLevel": { "Default": "Information", "Microsoft.AspNetCore": "Warning" } } | I5: The application only has basic logging configuration without structured logging or detailed context. Log events don't consistently include user IDs, timestamps, operation details, or request identifiers that would enable timeline reconstruction during security investigations. There's no standardized logging format or context enrichment across the application | J5: Structured logging with Serilog or NLog with context enrichers that add user identity, request ID, IP address, and timestamps. Use correlation IDs with ASP.NET Core's TraceIdentifier to link related events. For validation, create log analysis dashboards with tools like Seq or Kibana
A6: Log Processing | B6: 7.2.1 | C6: 2 | D6: 778 | F6: Verify that all authentication decisions are logged, without storing sensitive session identifiers or passwords. This should include requests with relevant metadata needed for security investigations. | G6: Valid | H6: AccountController.cs: _logger.LogInformation/Warning | I6: The application doesn't log authentication events. Successful and failed login attempts, signouts, and password changes aren't systematically logged. While the application handles these events correctly from a functional perspective, there's no audit trail of authentication activities that would be necessary for security monitoring and investigation | J6: Authentication event logging using ASP.NET Core Identity's SignInManager events or custom authentication middleware. Store logs securely in Application Insights or a SIEM system. Test with tools like Microsoft Sentinel or Splunk to verify log comprehensiveness
B7: 7.2.2 | C7: 2 | D7: 285 | F7: Verify that all access control decisions can be logged and all failed decisions are logged. This should include requests with relevant metadata needed for security investigations. | G7: Valid | H7: // ProductController.cs lines 28-34 (access control without logging) [HttpGet("{id}")] public IActionResult GetProduct(int id) { var product = _unitOfWork.Product.Get(p => p.Id == id && !p.IsDeleted, "Composites.SubProduct"); if (product == null) { return NotFound(new { message = "Product not found" }); } } | I7: The application implements access control through authorization attributes and explicit checks in controllers, but doesn't log these decisions. Failed access attempts return appropriate status codes but aren't recorded for security monitoring. There's no systematic logging of authorization decisions that would help detect potential security breaches | J7: Authorization logging middleware or filters that capture all access control decisions. Use policy-based authorization with IAuthorizationHandler implementations that include logging. Verify with log analysis tools like ELK Stack or Splunk to ensure comprehensive logging of access decisions
A8: Log Protection | B8: 7.3.1 | C8: 2 | D8: 117 | F8: Verify that all logging components appropriately encode data to prevent log injection. ([C9](https://owasp.org/www-project-proactive-controls/#div-numbering)) | G8: Non-valid | I8: The application doesn't have specific protections against log injection attacks. There's no evidence of log sanitization, encoding of user input before logging, or use of structured logging that would inherently protect against injection. This creates vulnerability to attacks where malicious user input could manipulate log records | J8: Structured logging with Serilog or NLog which inherently prevents most log injection attacks. Use logging libraries that escape special characters in log messages. Test with tools like OWASP ZAP or custom penetration testing scripts targeting logging mechanisms
B9: 7.3.2 | C9: 2 | D9: 117 | F9: [DELETED, DUPLICATE OF 7.3.1] | G9: Not Applicable
B10: 7.3.3 | C10: 2 | D10: 200 | F10: Verify that security logs are protected from unauthorized access and modification. ([C9](https://owasp.org/www-project-proactive-controls/#div-numbering)) | G10: Non-valid | I10: The application doesn't implement protection mechanisms for log files or logging infrastructure. There's no evidence of log integrity protection, access controls specific to logs, or secure log transmission. This leaves logs vulnerable to tampering or unauthorized access, which could compromise security investigations | J10: Tamper-evident logging with digital signatures or secure centralized logging with Syslog or a SIEM solution. Use file system ACLs or dedicated log management solutions that enforce access controls. Verify with security audit tools specific to log protection
B11: 7.3.4 | C11: 2 | F11: Verify that time sources are synchronized to the correct time and time zone. Strongly consider logging only in UTC if systems are global to assist with post-incident forensic analysis. ([C9](https://owasp.org/www-project-proactive-controls/#div-numbering)) | G11: Non-valid | I11: The application doesn't address time synchronization or standardized time formats in logs. There's no configuration to ensure consistent time sources across services, no standardization on UTC, and no timestamp formatting policy. This could complicate incident response and forensic analysis if logs from different components have inconsistent timestamps | J11: NTP synchronization at the server level and standardize on UTC in logging configuration. Use logging frameworks that support automatic timestamp conversion and formatting. Verify time synchronization with monitoring tools that check for time drift
A12: Error Handling | B12: 7.4.1 | C12: 1 | D12: 210 | F12: Verify that a generic message is shown when an unexpected or security sensitive error occurs, potentially with a unique ID which support personnel can use to investigate. ([C10](https://owasp.org/www-project-proactive-controls/#div-numbering)) | G12: Valid | H12: // ProductController.cs lines 30-33 (example of good practice) if (product == null) { return NotFound(new { message = "Product not found" }); } | I12: The application generally returns appropriate error messages with status codes for expected failure scenarios. However, there's no consistent error handling strategy for unexpected exceptions, no custom error pages or middleware that would present a generic message to users while logging detailed information internally. The application lacks a global exception handler that would maintain security while providing useful feedback | J12: ASP.NET Core's Exception Handling Middleware with custom error pages. Use Problem Details standard (RFC 7807) for structured error responses. Test with tools like Postman or custom scripts that trigger various error conditions
B13: 7.4.2 | C13: 2 | D13: 544 | F13: Verify that exception handling (or a functional equivalent) is used across the codebase to account for expected and unexpected error conditions. ([C10](https://owasp.org/www-project-proactive-controls/#div-numbering)) | G13: Valid | H13: // AMAP/AMAP.Data/DbInitializer/DbInitializer.cs lines 31-39 try { if (_db.Database.GetPendingMigrations().Count() > 0) { _db.Database.Migrate(); } } catch (Exception ex) { // Logar ou tratar o erro conforme necessário } | I13: The application has some exception handling in critical areas, but it's not consistently applied throughout the codebase. Many methods lack try-catch blocks, there's limited use of exception filters or middleware for handling exceptions, and no standardized approach to exception management. The DbInitializer example shows exception handling but with an empty catch block, which indicates incomplete implementation | J13: Global exception handling middleware, use exception filters for controller actions, and adopt a consistent try-catch pattern with proper logging. Use static analysis tools like Roslynator or SonarQube to identify areas lacking exception handling
B14: 7.4.3 | C14: 2 | D14: 431 | F14: Verify that a "last resort" error handler is defined which will catch all unhandled exceptions. ([C10](https://owasp.org/www-project-proactive-controls/#div-numbering)) | G14: Non-valid | I14: The application doesn't have a global or "last resort" error handler for unhandled exceptions. There's no UseExceptionHandler middleware configured in Program.cs, no custom error page for unexpected errors, and no mechanism to ensure all unhandled exceptions are logged while presenting a sanitized message to users. This omission could lead to detailed stack traces being exposed to users when unexpected errors occur | J14: ASP.NET Core's UseExceptionHandler middleware in Program.cs, create custom error pages for different error scenarios, and configure development vs. production error handling. Test with deliberate exceptions to verify that the last-resort handler catches all unhandled exceptions

Sheet Stored Cryptography
A1: Area | B1: # | C1: ASVS Level | D1: CWE | E1: NIST | F1: Verification Requirement | G1: Valid | H1: Source Code Reference | I1: Comment | J1: Tool Used
A2: Data Classification | B2: 6.1.1 | C2: 2 | D2: 311 | F2: Verify that regulated private data is stored encrypted while at rest, such as Personally Identifiable Information (PII), sensitive personal information, or data assessed likely to be subject to EU's GDPR. | G2: Non-valid | I2: The AMAP application stores personally identifiable information (PII) of users (e.g., names, emails), so encryption at rest is essential to comply with GDPR and protect against data exposure in the event of unauthorized access to the database (risks 3.1 I, 5.1 I). | J2: Transparent Data Encryption (TDE) in SQL Server, Always Encrypted, or encryption at the application level.
B3: 6.1.2 | C3: 2 | D3: 311 | F3: Verify that regulated health data is stored encrypted while at rest, such as medical records, medical device details, or de-anonymized research records. | G3: Non-valid
B4: 6.1.3 | C4: 2 | D4: 311 | F4: Verify that regulated financial data is stored encrypted while at rest, such as financial accounts, defaults or credit history, tax records, pay history, beneficiaries, or de-anonymized market or research records. | G4: Non-valid
A5: Algorithms | B5: 6.2.1 | C5: 1 | D5: 310 | F5: Verify that all cryptographic modules fail securely, and errors are handled in a way that does not enable Padding Oracle attacks. | G5: Valid | H5: // Em AMAP_API\Controllers\AccountController.cs [HttpPost("login")] [AllowAnonymous] public async Task<IActionResult> Login([FromBody] LoginViewModel loginViewModel) { if (ModelState.IsValid) { var result = await _signInManager.PasswordSignInAsync(loginViewModel.Email, loginViewModel.Password, loginViewModel.RememberMe, lockoutOnFailure: true); if (result.Succeeded) { var user = await _userManager.FindByEmailAsync(loginViewModel.Email); if (user == null) { return Unauthorized(new { message = "User not found" }); } // Obtem as roles dos users var roles = await _userManager.GetRolesAsync(user); return Ok(new { message = "Login successful", userId = user.Id, role = roles.FirstOrDefault() }); } if (result.IsLockedOut) { return StatusCode(423, new { message = "Account locked" }); } else { return Unauthorized(new { message = "Invalid login attempt" }); } } return BadRequest(ModelState); } | I5: A aplicação utiliza ASP.NET Identity para gestão de passwords, que trata erros de forma segura. No entanto, não há evidência de tratamento específico para falhas criptográficas. | J5: ASP.NET Core Identity
B6: 6.2.2 | C6: 2 | D6: 327 | F6: Verify that industry proven or government approved cryptographic algorithms, modes, and libraries are used, instead of custom coded cryptography. ([C8](https://owasp.org/www-project-proactive-controls/#div-numbering)) | G6: Valid | H6: // Em AMAP_API\Program.cs - Configuração do Identity builder.Services.AddIdentity<AppUser, IdentityRole>(options => { options.Password.RequiredLength = 12; // Min length 12 chars options.Password.RequireDigit = true; options.Password.RequireLowercase = true; options.Password.RequireUppercase = true; options.Password.RequireNonAlphanumeric = true; // Lockout settings options.Lockout.DefaultLockoutTimeSpan = TimeSpan.FromMinutes(15); options.Lockout.MaxFailedAccessAttempts = 5; options.Lockout.AllowedForNewUsers = true; // User settings options.User.RequireUniqueEmail = true; }) .AddEntityFrameworkStores<AppDbContext>() .AddDefaultTokenProviders() .AddPasswordValidator<CustomPasswordValidator<AppUser>>(); | I6: A aplicação usa ASP.NET Core Identity, que utiliza algoritmos padrão como PBKDF2 para hash de passwords. | J6: ASP.NET Core Identity
B7: 6.2.3 | C7: 2 | D7: 326 | F7: Verify that encryption initialization vector, cipher configuration, and block modes are configured securely using the latest advice. | G7: Non-valid
B8: 6.2.4 | C8: 2 | D8: 326 | F8: Verify that random number, encryption or hashing algorithms, key lengths, rounds, ciphers or modes, can be reconfigured, upgraded, or swapped at any time, to protect against cryptographic breaks. ([C8](https://owasp.org/www-project-proactive-controls/#div-numbering)) | G8: Valid | H8: // Em AMAP_API\Program.cs // Este trecho não está explícito no código fornecido, mas é possível adicionar: // Exemplo de como seria a configuração de opções do password hasher builder.Services.Configure<PasswordHasherOptions>(options => { options.IterationCount = 310000; // Aumentar o número de iterações options.CompatibilityMode = PasswordHasherCompatibilityMode.IdentityV3; // Versão mais recente }); | I8: ASP.NET Identity permite atualizar o algoritmo de hashing, mas não há suporte explícito para atualização de outros parâmetros criptográficos. | J8: ASP.NET Core Identity
B9: 6.2.5 | C9: 2 | D9: 326 | F9: Verify that known insecure block modes (i.e. ECB, etc.), padding modes (i.e. PKCS#1 v1.5, etc.), ciphers with small block sizes (i.e. Triple-DES, Blowfish, etc.), and weak hashing algorithms (i.e. MD5, SHA1, etc.) are not used unless required for backwards compatibility. | G9: Valid | H9: // Em AMAP_API\Program.cs // A configuração do Identity, conforme mostrada acima, utiliza o PasswordHasher // que implementa PBKDF2-SHA256 por padrão, que é considerado seguro builder.Services.AddIdentity<AppUser, IdentityRole>(options => { // Configurações de segurança de senha }) .AddEntityFrameworkStores<AppDbContext>() .AddDefaultTokenProviders(); | I9: Não foi identificado o uso de algoritmos fracos. O sistema usa PBKDF2 através do ASP.NET Identity, que é seguro. | J9: ASP.NET Core Identity
B10: 6.2.6 | C10: 2 | D10: 326 | F10: Verify that nonces, initialization vectors, and other single use numbers must not be used more than once with a given encryption key. The method of generation must be appropriate for the algorithm being used. | G10: Non-valid
B11: 6.2.7 | C11: 3 | D11: 326 | F11: Verify that encrypted data is authenticated via signatures, authenticated cipher modes, or HMAC to ensure that ciphertext is not altered by an unauthorized party. | G11: Non-valid
B12: 6.2.8 | C12: 3 | D12: 385 | F12: Verify that all cryptographic operations are constant-time, with no 'short-circuit' operations in comparisons, calculations, or returns, to avoid leaking information. | G12: Non-valid
A13: Random values | B13: 6.3.1 | C13: 2 | D13: 338 | F13: Verify that all random numbers, random file names, random GUIDs, and random strings are generated using the cryptographic module's approved cryptographically secure random number generator when these random values are intended to be not guessable by an attacker. | G13: Valid | H13: // Em AMAP.Business\Components\ProductBc.cs (linha 296) // Geração de um nome de arquivo único usando GUID v4 string uniqueFileName = $"{Guid.NewGuid()}_{safeFileName}"; | I13: A aplicação usa Guid.NewGuid() para gerar nomes de ficheiros únicos em ProductBc.cs (linha 296), o que é seguro (GUID v4), mas não utiliza explicitamente RandomNumberGenerator noutros casos. | J13: System.Guid (classe padrão do .NET Framework)
B14: 6.3.2 | C14: 2 | D14: 338 | F14: Verify that random GUIDs are created using the GUID v4 algorithm, and a Cryptographically-secure Pseudo-random Number Generator (CSPRNG). GUIDs created using other pseudo-random number generators may be predictable. | G14: Valid | H14: // Em AMAP.Business\Components\ProductBc.cs (linha 296) // Geração de um nome de arquivo único usando GUID v4 string uniqueFileName = $"{Guid.NewGuid()}_{safeFileName}"; | I14: A aplicação utiliza Guid.NewGuid(), que gera GUIDs v4 com base em valores criptograficamente seguros. | J14: System.Guid (classe padrão do .NET Framework)
B15: 6.3.3 | C15: 3 | D15: 338 | F15: Verify that random numbers are created with proper entropy even when the application is under heavy load, or that the application degrades gracefully in such circumstances. | G15: Non-valid
A16: Secret Management | B16: 6.4.1 | C16: 2 | D16: 798 | F16: Verify that a secrets management solution such as a key vault is used to securely create, store, control access to and destroy secrets. ([C8](https://owasp.org/www-project-proactive-controls/#div-numbering)) | G16: Valid | H16: // Em AMAP_API\AMAP.Api.csproj <PropertyGroup> <TargetFramework>net9.0</TargetFramework> <Nullable>enable</Nullable> <ImplicitUsings>enable</ImplicitUsings> <UserSecretsId>2399dae3-8ae7-46c0-9bd6-806ab88f52f5</UserSecretsId> </PropertyGroup> | I16: A aplicação usa o UserSecrets do .NET no projeto .csproj, adequado para desenvolvimento local. | J16: Microsoft.Extensions.Configuration.UserSecrets (ASP.NET Core Secret Manager)
B17: 6.4.2 | C17: 2 | D17: 320 | F17: Verify that key material is not exposed to the application but instead uses an isolated security module like a vault for cryptographic operations. ([C8](https://owasp.org/www-project-proactive-controls/#div-numbering)) | G17: Valid | H17: // Em AMAP_API\Program.cs builder.Services.AddIdentity<AppUser, IdentityRole>(options => { // Configurações de senha e segurança }) .AddEntityFrameworkStores<AppDbContext>() .AddDefaultTokenProviders(); | I17: A aplicação usa o ASP.NET Core Identity, mas não utiliza um módulo externo para operações criptográficas – depende do mecanismo interno do framework. | J17: ASP.NET Core Identity Framework

Sheet Communication
A1: Area | B1: # | C1: ASVS Level | D1: CWE | E1: NIST | F1: Verification Requirement | G1: Valid | H1: Source Code Reference | I1: Comment | J1: Tool Used
A2: Client Communications Security | B2: 9.1.1 | C2: 1 | D2: 319 | F2: Verify that TLS is used for all client connectivity, and does not fall back to insecure or unencrypted communications. ([C8](https://owasp.org/www-project-proactive-controls/#div-numbering)) | G2: Valid | H2: // Program.cs line 131 app.UseHttpsRedirection(); // Program.cs lines 67-70 (Development environment configuration) if (builder.Environment.IsDevelopment()) { options.Cookie.SecurePolicy = CookieSecurePolicy.None; // Permitir HTTP options.Cookie.SameSite = SameSiteMode.None; // Permitir cross-origin } // Program.cs lines 99-101 (Session cookie configuration) options.Cookie.HttpOnly = true; options.Cookie.IsEssential = true; options.Cookie.SecurePolicy = CookieSecurePolicy.None; // Permitir envio em HTTP | I2: The application implements HTTPS redirection but has critical flaws that allow fallback to insecure communications. While web traffic uses HTTPS through UseHttpsRedirection(), the session cookie settings explicitly allow insecure transport with SecurePolicy=None. Development environment settings disable secure cookies, but there's no guarantee these won't be carried into production. Additionally, there's no HTTP Strict Transport Security (HSTS) implementation to prevent downgrade attacks. The application requires a consistent security policy that enforces encrypted communications across all client connectivity without exceptions | J2: ASP.NET Core's HSTS middleware with app.UseHsts() in Program.cs for production environments. Set all cookies to require HTTPS with SecurePolicy=Always. Use Qualys SSL Labs or OWASP ZAP to test for TLS implementation issues and potential downgrade vulnerabilities. Configure Content-Security-Policy headers to enforce HTTPS for all resources. For comprehensive inspection, tools like Burp Suite can verify that all client communications remain encrypted without fallback options
B3: 9.1.2 | C3: 1 | D3: 326 | F3: Verify using up to date TLS testing tools that only strong cipher suites are enabled, with the strongest cipher suites set as preferred. | G3: Valid | I3: O ASP.NET Core, por omissão, utiliza cipher suites fortes e recomendados.Não há configuração personalizada de cipher suites, mas o padrão é seguro para ambientes modernos.
B4: 9.1.3 | C4: 1 | D4: 326 | F4: Verify that only the latest recommended versions of the TLS protocol are enabled, such as TLS 1.2 and TLS 1.3. The latest version of the TLS protocol should be the preferred option. | G4: Valid | I4: O ASP.NET Core suporta apenas TLS 1.2+ por omissão em ambientes modernos.Não há suporte para versões antigas/inseguras do TLS.
A5: Server Communication Security | B5: 9.2.1 | C5: 2 | D5: 295 | F5: Verify that connections to and from the server use trusted TLS certificates. Where internally generated or self-signed certificates are used, the server must be configured to only trust specific internal CAs and specific self-signed certificates. All others should be rejected. | G5: Valid | I5: O servidor utiliza TLS com certificados válidos em produção.Em desenvolvimento pode usar self-signed, mas em produção só certificados de CA confiáveis são aceites. | J5: X509Certificate2 validation can be implemented with custom validation callbacks in HttpClientHandler. For server certificates, we could use ASP.NET Core's certificate configuration in Program.cs. Certificate validation can be tested with tools like OpenSSL or specialized security scanners like Burp Suite.
B6: 9.2.2 | C6: 2 | D6: 319 | F6: Verify that encrypted communications such as TLS is used for all inbound and outbound connections, including for management ports, monitoring, authentication, API, or web service calls, database, cloud, serverless, mainframe, external, and partner connections. The server must not fall back to insecure or unencrypted protocols. | G6: Valid | H6: // Program.cs line 131 app.UseHttpsRedirection(); // Connection String in appsettings.json line 28 "DefaultConnection": "Data Source=DIOGO\\SQLEXPRESS;Initial Catalog=AMAP_DB;Integrated Security=True;Encrypt=False;" // EmailSender.cs line 36 EnableSsl = true | I6: The application has inconsistent encryption across different connections. While HTTPS is enforced for web traffic through UseHttpsRedirection() and email communication uses EnableSsl=true, database connections explicitly disable encryption with Encrypt=False. All connections should use encryption, including database connections, to ensure comprehensive security | J6: SQL Server connection strings with Encrypt=True, ensure HTTPS for all outbound HttpClient calls, and configure TLS for all service connections. OWASP ZAP or Burp Suite can scan for unencrypted connections
B7: 9.2.3 | C7: 2 | D7: 287 | F7: Verify that all encrypted connections to external systems that involve sensitive information or functions are authenticated. | G7: Valid | H7: // EmailSender.cs lines 35-36 Credentials = new NetworkCredential(_username, _password), EnableSsl = true // Program.cs line 34 builder.Services.AddIdentity<AppUser, IdentityRole>() .AddEntityFrameworkStores<AppDbContext>() .AddDefaultTokenProviders(); | I7: Basic authentication is implemented for some external connections. Email service uses credential-based authentication with SSL, and API endpoints are secured with ASP.NET Identity. However, there's no comprehensive authentication strategy for all external services, no client certificate authentication, and no API key validation for third-party services | J7: mutual TLS (mTLS) authentication, OAuth 2.0 for API authentication, and credential management tools like Azure Key Vault or AWS Secrets Manager for secure credential storage
B8: 9.2.4 | C8: 2 | D8: 299 | F8: Verify that proper certification revocation, such as Online Certificate Status Protocol (OCSP) Stapling, is enabled and configured. | G8: Non-valid | I8: The application has no certificate revocation checking mechanisms. It doesn't implement or configure OCSP Stapling, CRL checking, or any method to verify that certificates haven't been revoked. This is a significant security gap that could allow connections with compromised certificates | J8: For ASP.NET Core, we could configure HttpClientHandler with CheckCertificateRevocationList=true for outbound connections. For server configuration, implement OCSP Stapling in Kestrel or IIS. OpenSSL can be used to test certificate revocation status
B9: 9.2.5 | C9: 3 | D9: 544 | F9: Verify that backend TLS connection failures are logged. | G9: Non-valid | I9: Não há evidência de logging específico para falhas de ligação TLS a serviços backend.

Sheet Data Protection
A1: Area | B1: # | C1: ASVS Level | D1: CWE | E1: NIST | F1: Verification Requirement | G1: Valid | H1: Source Code Reference | I1: Comment | J1: Tool Used
A2: General Data Protection | B2: 8.1.1 | C2: 2 | D2: 524 | F2: Verify the application protects sensitive data from being cached in server components such as load balancers and application caches. | G2: Valid | H2: AMAP/AMAP_API/Program.cs (Session and authentication cookie configuration without response caching, and with HttpOnly, Secure and SameSite=Strict in production). <br> AMAP/AMAP_API/Controllers/AccountController.cs (No [ResponseCache] attribute on actions handling authentication and user data). <br> AMAP/AMAP_API/Controllers/PaymentsInfoController.cs (No [ResponseCache] attribute on actions returning financial information). <br> AMAP/AMAP_API/Controllers/PaymentController.cs (No [ResponseCache] attribute on actions handling payments). | I2: The application adequately protects sensitive data from being cached in server components such as load balancers and application caches. There are no cache control directives for sensitive API responses, and no cache control attributes are implemented on controller methods that handle sensitive data. The authentication cookie configurations (HttpOnly, Secure, SameSite=Strict in production) and session configurations ensure that sensitive data does not persist in cache. | J2: ASP.NET Core Identity's Cookie Authentication (ConfigureApplicationCookie options like HttpOnly, SecurePolicy, SameSite), Absence of [ResponseCache] attribute, Lack of explicit response caching middleware for sensitive endpoints.
B3: 8.1.2 | C3: 2 | D3: 524 | F3: Verify that all cached or temporary copies of sensitive data stored on the server are protected from unauthorized access or purged/invalidated after the authorized user accesses the sensitive data. | G3: Valid | H3: AMAP/AMAP_API/Program.cs (Configuration for session IdleTimeout and secure authentication cookie settings: HttpOnly, SecurePolicy.Always in production, SameSite.Strict in production). <br> AMAP/AMAP_API/Controllers/AccountController.cs (The LogOff action explicitly invalidates the user's authentication cookie and session upon logout). | I3: The application does not store sensitive data in response caches. Sensitive temporary data, primarily user sessions, are stored in server-side memory (IDistributedMemoryCache). These sessions are protected by secure authentication cookie settings (HttpOnly, SecurePolicy.Always in production, SameSite.Strict in production) which prevent unauthorized access. Sessions are automatically purged/invalidated after an IdleTimeout (100 minutes) or explicitly upon user logout, ensuring sensitive data does not persist unnecessarily. | J3: ASP.NET Core Session Management (AddDistributedMemoryCache, AddSession with IdleTimeout), ASP.NET Core Identity's Cookie Authentication (ConfigureApplicationCookie options like HttpOnly, SecurePolicy, SameSite), ASP.NET Core Identity's SignInManager.SignOutAsync().
B4: 8.1.3 | C4: 2 | D4: 233 | F4: Verify the application minimizes the number of parameters in a request, such as hidden fields, Ajax variables, cookies and header values. | G4: Valid | H4: // ProductController.cs - Example of good practice with minimal parameters [HttpGet("{id}")] public IActionResult GetProduct(int id) { var product = _unitOfWork.Product.Get(p => p.Id == id && !p.IsDeleted, "Composites.SubProduct"); // ... } | I4: The application generally uses concise models for data transfer, with controllers accepting minimal parameters where possible. However, there's no consistent strategy to minimize parameters across all endpoints. Some endpoints may include more parameters than necessary, and there's no apparent review process to ensure minimal data transfer. The codebase would benefit from standardizing on concise parameter patterns | J4: DTOs (Data Transfer Objects) consistently to control parameter exposure. Use custom model binders or JsonIgnore attributes to limit serialized parameters. Tools like Swagger/OpenAPI can document and analyze API surface exposure
B5: 8.1.4 | C5: 2 | D5: 770 | F5: Verify the application can detect and alert on abnormal numbers of requests, such as by IP, user, total per hour or day, or whatever makes sense for the application. | G5: Valid | H5: AMAP/AMAP_API/Program.cs (ASP.NET Core AddRateLimiter and UseRateLimiter middleware with FixedWindowLimiter partitioned by RemoteIpAddress; ASP.NET Core Identity's Lockout settings for MaxFailedAccessAttempts and DefaultLockoutTimeSpan; builder.Logging.AddFilter for LogLevel.Information on AccountController). <br> AMAP/AMAP_API/Logs/security-20250522.txt (Logging of login attempts, including UnauthorizedObjectResult and BadRequestObjectResult). | I5: The application now implements a global rate-limiting mechanism per IP address to protect against abnormal request volumes, including DoS attacks. Additionally, it maintains a lockout mechanism for user accounts based on failed login attempts. Extensive logging of requests, particularly from the AccountController, provides the necessary data for external monitoring and alerting systems to detect and notify of abnormal patterns. | J5: ASP.NET Core Rate Limiting (AddRateLimiter, UseRateLimiter, FixedWindowLimiter), ASP.NET Core Identity (LockoutEnabled, MaxFailedAccessAttempts, DefaultLockoutTimeSpan), ASP.NET Core Logging (Microsoft.Extensions.Logging).
B6: 8.1.5 | C6: 3 | D6: 19 | F6: Verify that regular backups of important data are performed and that test restoration of data is performed. | G6: Valid | H6: backup/README.md (Documentation outlining backup and restore procedures, including the recommendation to test restorations). backup/backup-database.ps1 (PowerShell script for performing full database backups with retention and logging). backup/restore-database.ps1 (PowerShell script for restoring the database from a backup file). backup/schedule-backup.ps1 (Implicitly supported by README.md instructions for Windows Task Scheduler). | I6: The project provides a set of PowerShell scripts and clear documentation (README.md) that enable the performance of regular database backups and, critically, facilitate the testing of these restorations. While the actual execution of these processes (regular backups and test restorations) depends on operational procedures and infrastructure configuration, the necessary tools and guidelines are present within the codebase. | J6: PowerShell scripts (.ps1), Documentation (Markdown).
B7: 8.1.6 | C7: 3 | D7: 19 | F7: Verify that backups are stored securely to prevent data from being stolen or corrupted. | G7: Non-valid | I7: The application doesn't implement any backup security measures. There's no encryption for backup data, no access controls specific to backups, and no integrity validation for backup files. Security considerations for backup storage are entirely absent from the codebase | J7: Encryption for backups using libraries like Azure Storage Client with encryption, or BouncyCastle for custom encryption. Use secure storage services like Azure Blob Storage with access policies. For validation, tools like Azure Security Center or custom security auditing scripts could verify backup security
A8: Client-side Data Protection | B8: 8.2.1 | C8: 1 | D8: 525 | F8: Verify the application sets sufficient anti-caching headers so that sensitive data is not cached in modern browsers. | G8: Valid | H8: AMAP/AMAP_API/Controllers/PaymentsInfoController.cs ([ResponseCache(NoStore = true, Location = ResponseCacheLocation.None, Duration = 0)] attribute applied). <br> AMAP/AMAP_API/Controllers/AccountController.cs ([ResponseCache(NoStore = true, Location = ResponseCacheLocation.None, Duration = 0)] attribute applied). <br> AMAP/AMAP_API/Controllers/PaymentController.cs ([ResponseCache(NoStore = true, Location = ResponseCacheLocation.None, Duration = 0)] attribute applied). | I8: The application now explicitly sets anti-caching HTTP headers (e.g., Cache-Control: no-store, no-cache, Pragma: no-cache) for responses containing sensitive data by applying the [ResponseCache(NoStore = true, Location = ResponseCacheLocation.None, Duration = 0)] attribute to relevant controllers. This ensures that sensitive information is not cached by client browsers or intermediate proxies. | J8: ASP.NET Core [ResponseCache] attribute (NoStore, Location, Duration).
B9: 8.2.2 | C9: 1 | D9: 922 | F9: Verify that data stored in browser storage (such as localStorage, sessionStorage, IndexedDB, or cookies) does not contain sensitive data. | G9: Non-valid | H9: // amap-ui/src/pages/LoginSignUp.js lines 26-32 localStorage.setItem('userType', role); localStorage.setItem('userId', userId); | I9: The application stores user identifiers in localStorage, which is not secure for sensitive data. User IDs could be considered sensitive as they can be used for identification. Additionally, there's no clear policy on what client-side storage can or cannot contain, and no encryption for any data stored in browser storage | J9: We could replace localStorage with sessionStorage for authentication tokens and implement cookie-based authentication with secure and HTTPOnly flags. For any client-side data persistence needs, encrypt sensitive data before storing. Use tools like OWASP ZAP or browser security extensions to audit client-side storage
B10: 8.2.3 | C10: 1 | D10: 922 | F10: Verify that authenticated data is cleared from client storage, such as the browser DOM, after the client or session is terminated. | G10: Valid | H10: The amap-ui/src/pages/LoginSignUp.js (Stores userId and userType in sessionStorage). The amap-ui/src/service/subscriptionService.js, amap-ui/src/service/productService.js, amap-ui/src/service/offerService.js (Read from sessionStorage). The amap-ui/src/components/Sidebar.js (Reads userType from sessionStorage, implements handleLogout to call backend logout, clear sessionStorage and localStorage, and redirect). | I10: Authenticated data (userId, userType, and authToken from sessionStorage) is now stored in sessionStorage, ensuring it is automatically cleared when the browser tab/window is closed. Furthermore, an explicit client-side logout mechanism has been implemented. Upon logout, a request is sent to the backend to invalidate the server-side session, and the sessionStorage (and localStorage for completeness) is explicitly cleared, preventing sensitive authenticated data from persisting on the client after session termination. | J10: Frontend sessionStorage API, JavaScript fetch API (for backend logout), JavaScript sessionStorage.clear(), JavaScript localStorage.clear().
A11: Sensitive Private Data | B11: 8.3.1 | C11: 1 | D11: 319 | F11: Verify that sensitive data is sent to the server in the HTTP message body or headers, and that query string parameters from any HTTP verb do not contain sensitive data. | G11: Valid | H11: // AccountController.cs lines 30-37 [HttpPost("login")] [AllowAnonymous] public async Task<IActionResult> Login([FromBody] LoginViewModel loginViewModel) { // Credentials passed in body, not URL } | I11: For authentication, the application properly uses HTTP POST with body parameters rather than query strings. However, there's no consistent protection across all endpoints to prevent sensitive data in query strings. No specific validation exists to ensure all sensitive operations use body parameters instead of query parameters | J11: [FromBody] attribute consistently for all sensitive data transfers, implement API gateway filtering or middleware that rejects sensitive parameters in query strings. Tools like Fiddler or OWASP ZAP can analyze request patterns to identify sensitive data in query strings
B12: 8.3.2 | C12: 1 | D12: 212 | F12: Verify that users have a method to remove or export their data on demand. | G12: Non-valid | I12: The application doesn't provide functionality for users to export or delete their personal data. There are no endpoints or services dedicated to data portability or account deletion. This is a significant gap for GDPR and other privacy regulation compliance | J12: Implement dedicated controllers/endpoints for data export (providing user data in machine-readable format) and account deletion. Create services that can gather all user-related data across tables. Test with tools like Postman collections that validate the completeness of exported data
B13: 8.3.3 | C13: 1 | D13: 285 | F13: Verify that users are provided clear language regarding collection and use of supplied personal information and that users have provided opt-in consent for the use of that data before it is used in any way. | G13: Non-valid | I13: The application has no consent management system, privacy notifications, or opt-in mechanisms. There's no evidence of privacy policy presentation to users or consent tracking in the database. The application does not comply with modern privacy regulations that require explicit consent | J13: Consent management system with dedicated models for storing user consent. Create UI components for privacy notices and consent gathering. For validation, tools like Cookie Consent Management platforms or custom audit logs can track consent collection
B14: 8.3.4 | C14: 1 | D14: 200 | F14: Verify that all sensitive data created and processed by the application has been identified, and ensure that a policy is in place on how to deal with sensitive data. ([C8](https://owasp.org/www-project-proactive-controls/#div-numbering)) | G14: Non-valid | I14: The application lacks data classification, sensitivity tagging, or explicit policies on handling different types of data. There are no annotations or markers identifying which fields contain sensitive information, and no code-level enforcement of handling policies for different data sensitivity levels | J14: Data annotations or attributes that mark sensitive fields, create a data classification service that enforces handling policies based on classifications. Use static analysis tools like SonarQube with custom rules to detect potential mishandling of marked sensitive data
B15: 8.3.5 | C15: 2 | D15: 532 | F15: Verify accessing sensitive data is audited (without logging the sensitive data itself), if the data is collected under relevant data protection directives or where logging of access is required. | G15: Non-valid | I15: The application has no comprehensive audit logging system for sensitive data access. There are no audit trails recording when sensitive information is viewed, modified, or deleted. Without this auditing, the application cannot detect or investigate potential data breaches or unauthorized access | J15: AuditTrail middleware or aspect-oriented programming approaches with PostSharp to automatically log access to sensitive controllers/actions. Use tools like Application Insights or Serilog with structured logging to create queryable audit trails
B16: 8.3.6 | C16: 2 | D16: 226 | F16: Verify that sensitive information contained in memory is overwritten as soon as it is no longer required to mitigate memory dumping attacks, using zeroes or random data. | G16: Non-valid | I16: The application doesn't implement memory sanitization for sensitive data. There's no use of SecureString for storing passwords or encryption keys, and no explicit overwriting of memory containing sensitive data after use. This creates vulnerability to memory dump attacks | J16: SecureString for passwords and encryption keys, implement explicit memory clearing with Array.Clear() or Buffer.BlockCopy() to overwrite sensitive data when no longer needed. Tools like dotMemory can help detect sensitive data remnants in memory after operations complete
B17: 8.3.7 | C17: 2 | D17: 327 | F17: Verify that sensitive or private information that is required to be encrypted, is encrypted using approved algorithms that provide both confidentiality and integrity. ([C8](https://owasp.org/www-project-proactive-controls/#div-numbering)) | G17: Non-valid | I17: The application doesn't implement encryption for sensitive data at rest or in transit beyond HTTPS. Database connection strings have encryption explicitly disabled with "Encrypt=False". There's no use of cryptographic libraries for field-level encryption of sensitive data, leaving PII and other sensitive information vulnerable | J17: Data protection using ASP.NET Core Data Protection APIs, use EF Core value converters for transparent field-level encryption, and enable SQL Server Transparent Data Encryption. For validation, use tools like OWASP Dependency Check to verify cryptographic libraries and OWASP ZAP to test encrypted communications
B18: 8.3.8 | C18: 2 | D18: 285 | F18: Verify that sensitive personal information is subject to data retention classification, such that old or out of date data is deleted automatically, on a schedule, or as the situation requires. | G18: Non-valid | I18: The application has no data retention policies or automatic purging of outdated personal information. There are no scheduled jobs to anonymize or delete old data, and no classification system to determine retention periods for different types of data. This creates compliance issues with privacy regulations that require limiting data retention | J18: Data retention service with scheduled jobs using Quartz.NET or Hangfire, create data classification attributes that specify retention periods, and develop purging or anonymization routines. Create audit reports using custom queries or Power BI to verify compliance with retention policies

Sheet Configuration
A1: Area | B1: # | C1: ASVS Level | D1: CWE | E1: NIST | F1: Verification Requirement | G1: Valid | H1: Source Code Reference | I1: Comment | J1: Tool Used
A2: Build and Deploy | B2: 14.1.1 | C2: 2 | F2: Verify that the application build and deployment processes are performed in a secure and repeatable way, such as CI / CD automation, automated configuration management, and automated deployment scripts. | G2: Valid | I2: O projeto utiliza CI/CD automatizado (GitHub Actions), scripts de build e deploy, e gestão automatizada de configurações.
B3: 14.1.2 | C3: 2 | D3: 120 | F3: Verify that compiler flags are configured to enable all available buffer overflow protections and warnings, including stack randomization, data execution prevention, and to break the build if an unsafe pointer, memory, format string, integer, or string operations are found. | G3: Valid | I3: O .NET por omissão ativa proteções de memória e warnings críticos.O pipeline de build falha em caso de erros graves ou warnings configurados como erros.
B4: 14.1.3 | C4: 2 | D4: 16 | F4: Verify that server configuration is hardened as per the recommendations of the application server and frameworks in use. | G4: Valid | I4: O projeto segue recomendações de hardening do ASP.NET Core (ex: HTTPS obrigatório, cookies seguros, CORS restritivo, logging seguro).
B5: 14.1.4 | C5: 2 | F5: Verify that the application, configuration, and all dependencies can be re-deployed using automated deployment scripts, built from a documented and tested runbook in a reasonable time, or restored from backups in a timely fashion. | G5: Valid | I5: O deploy é automatizado via scripts e CI/CD.Existe documentação e scripts para restauro rápido a partir de backups.
B6: 14.1.5 | C6: 3 | F6: Verify that authorized administrators can verify the integrity of all security-relevant configurations to detect tampering. | G6: Non-valid | I6: Não existe mecanismo explícito para verificação de integridade das configurações de segurança (ex: checksums, auditoria de alterações, etc.).
A7: Dependency | B7: 14.2.1 | C7: 1 | D7: 1026 | F7: Verify that all components are up to date, preferably using a dependency checker during build or compile time. ([C2](https://owasp.org/www-project-proactive-controls/#div-numbering)) | G7: Valid | H7: <!-- AMAP.Api.csproj lines 10-24 (dependencies without version checking) --> <ItemGroup> <PackageReference Include="Microsoft.AspNetCore.Authentication.JwtBearer" Version="9.0.4" /> <PackageReference Include="Microsoft.AspNetCore.Cors" Version="2.2.0" /> <PackageReference Include="Microsoft.AspNetCore.Identity.EntityFrameworkCore" Version="9.0.4" /> <PackageReference Include="Microsoft.EntityFrameworkCore" Version="9.0.4" /> <!-- Additional dependencies --> </ItemGroup> | I7: The application uses NuGet packages with specific versions, but there's no automated dependency checking to ensure these are the latest secure versions. No dependency scanning tools are integrated into the build process to identify vulnerabilities in dependencies. While the current dependency versions appear recent, there's no systematic process to keep them updated | J7: OWASP Dependency-Check, Snyk, or WhiteSource into the CI/CD pipeline. Configure dependabot for GitHub repositories to automatically suggest dependency updates. Use Visual Studio's built-in security vulnerability detection or NuGet Package Explorer to audit dependencies
B8: 14.2.2 | C8: 1 | D8: 1002 | F8: Verify that all unneeded features, documentation, sample applications and configurations are removed. | G8: Valid | I8: The application contains commented-out code, unused authentication configuration, and potentially unnecessary dependencies. There's no evidence of a clean production build process that removes development artifacts. The presence of Swagger in production depends on the environment variable, but there's no systematic removal of other development features | J8: Build profiles that strip out debugging information and development dependencies. Use .gitignore to prevent committing development artifacts. Create deployment scripts that generate clean production builds. For validation, scan production deployments with security tools to detect unnecessary components
B9: 14.2.3 | C9: 1 | D9: 829 | F9: Verify that if application assets, such as JavaScript libraries, CSS stylesheets or web fonts, are hosted externally on a content delivery network (CDN) or external provider, Subresource Integrity (SRI) is used to validate the integrity of the asset. | G9: Not Applicable | I9: O sistema AMAP não utiliza assets externos via CDN (nem JS, CSS, fontes externas).
B10: 14.2.4 | C10: 2 | D10: 829 | F10: Verify that third party components come from pre-defined, trusted and continually maintained repositories. ([C2](https://owasp.org/www-project-proactive-controls/#div-numbering)) | G10: Valid | H10: <!-- AMAP.Api.csproj lines 10-24 (standard NuGet packages) --> <ItemGroup> <PackageReference Include="Microsoft.AspNetCore.Authentication.JwtBearer" Version="9.0.4" /> <!-- Other standard packages --> </ItemGroup> | I10: Todas as dependências são obtidas de repositórios oficiais (NuGet). | J10: NuGet.config file that specifies trusted package sources. Implement package signature verification with NuGet trusted signers. For non-.NET dependencies, use tools like npm audit or Yarn's integrity checking. Validate with dependency governance tools like WhiteSource
B11: 14.2.5 | C11: 2 | F11: Verify that a Software Bill of Materials (SBOM) is maintained of all third party libraries in use. ([C2](https://owasp.org/www-project-proactive-controls/#div-numbering)) | G11: Valid | I11: O inventário de dependências é gerado automaticamente e documentado (ex: dotnet list package, relatórios Snyk/OWASP).
B12: 14.2.6 | C12: 2 | D12: 265 | F12: Verify that the attack surface is reduced by sandboxing or encapsulating third party libraries to expose only the required behaviour into the application. ([C2](https://owasp.org/www-project-proactive-controls/#div-numbering)) | G12: Valid | I12: As bibliotecas de terceiros são usadas apenas através das APIs públicas e seguras, sem exposição direta de funcionalidades desnecessárias.
A13: Unintended Security Disclosure | B13: 14.3.1 | C13: 1 | D13: 209 | F13: [DELETED, DUPLICATE OF 7.4.1] | G13: Not Applicable
B14: 14.3.2 | C14: 1 | D14: 497 | F14: Verify that web or application server and application framework debug modes are disabled in production to eliminate debug features, developer consoles, and unintended security disclosures. | G14: Valid | H14: // Program.cs lines 126-130 if (app.Environment.IsDevelopment()) { app.UseSwagger(); app.UseSwaggerUI(); } | I14: The application correctly configures debug features to be available only in the development environment. Swagger UI, which could expose sensitive API information, is only enabled in development mode. The environment-based configuration is properly implemented, preventing debug information disclosure in production | J14: We should continue using environment-based configuration with IsDevelopment() checks. Consider additional preprocessor directives for debug code. For validation, use penetration testing tools like OWASP ZAP to verify that development features aren't accessible in production
B15: 14.3.3 | C15: 1 | D15: 200 | F15: Verify that the HTTP headers or any part of the HTTP response do not expose detailed version information of system components. | G15: Valid | I15: O ASP.NET Core, por omissão, não expõe headers com versões detalhadas do framework ou componentes.Não há código que adicione manualmente informações de versão nas respostas HTTP.
A16: HTTP Security Headers | B16: 14.4.1 | C16: 1 | D16: 173 | F16: Verify that every HTTP response contains a Content-Type header. Also specify a safe character set (e.g., UTF-8, ISO-8859-1) if the content types are text/*, /+xml and application/xml. Content must match with the provided Content-Type header. | G16: Valid | H16: // ProductController.cs lines 28-41 (implicit Content-Type) [HttpGet("{id}")] public IActionResult GetProduct(int id) { // ... return Ok(new { product.Id, product.Name, // ... }); } | I16: The application implicitly sets Content-Type headers through ASP.NET Core's content negotiation and response formatting. Controllers return IActionResult types that typically resolve to JSON with appropriate Content-Type headers. However, there's no explicit policy enforcing Content-Type headers for all responses, and no verification that text/* responses include character set specifications | J16: Response formatting middleware that ensures appropriate Content-Type headers with character sets. Use content negotiation options in ASP.NET Core to enforce consistent formatting. Validate with HTTP analyzers or tools like Fiddler that can inspect response headers
B17: 14.4.2 | C17: 1 | D17: 116 | F17: Verify that all API responses contain Content-Disposition: attachment; filename="api.json" header (or other appropriate filename for the content type). | G17: Valid | I17: The application doesn't set Content-Disposition headers for API responses. There's no middleware or filter that adds these headers automatically, and no controller actions explicitly set them. This omission could potentially allow API responses to be rendered inline in a browser context, facilitating certain types of attacks | J17: Global filter or middleware that adds Content-Disposition headers to API responses. Use FileResult with FileDownloadName for file downloads. Validate with tools that can inspect HTTP headers such as browser developer tools or Fiddler
B18: 14.4.3 | C18: 1 | D18: 1021 | F18: Verify that a Content Security Policy (CSP) response header is in place that helps mitigate impact for XSS attacks like HTML, DOM, JSON, and JavaScript injection vulnerabilities. | G18: Non-valid | H18: Não há configuração explícita de header CSP nas respostas. | I18: The application doesn't implement Content Security Policy headers. There's no middleware configuration for CSP, no policy definition in the code, and no headers that would mitigate XSS attacks. This significant security gap leaves the application vulnerable to various injection attacks | J18: NWebsec middleware for ASP.NET Core to add CSP headers. Configure a strict CSP policy that limits script sources, style sources, and other resources. Validate with securityheaders.com or Mozilla Observatory to test CSP effectiveness
